[
  {
    "date": "2004-12-31",
    "base": "EUR",
    "rates": {
      "USD": 1.3621,
      "JPY": 139.65,
      "BGN": 1.9559,
      "CYP": 0.58,
      "CZK": 30.464,
      "DKK": 7.4388,
      "EEK": 15.6466,
      "GBP": 0.70505,
      "HUF": 245.97,
      "LTL": 3.4528,
      "LVL": 0.6979,
      "MTL": 0.4343,
      "PLN": 4.0845,
      "ROL": 39390,
      "SEK": 9.0206,
      "SIT": 239.76,
      "SKK": 38.745,
      "CHF": 1.5429,
      "ISK": 83.6,
      "NOK": 8.2365,
      "TRL": 1836200,
      "AUD": 1.7459,
      "CAD": 1.6416,
      "HKD": 10.5881,
      "KRW": 1410.05,
      "NZD": 1.8871,
      "SGD": 2.2262,
      "ZAR": 7.6897
    }
  },
  {
    "date": "2004-12-30",
    "base": "EUR",
    "rates": {
      "USD": 1.3604,
      "JPY": 141.03,
      "BGN": 1.9559,
      "CYP": 0.5796,
      "CZK": 30.395,
      "DKK": 7.4381,
      "EEK": 15.6466,
      "GBP": 0.7088,
      "HUF": 245.63,
      "LTL": 3.4528,
      "LVL": 0.698,
      "MTL": 0.4346,
      "PLN": 4.074,
      "ROL": 39465,
      "SEK": 9.0155,
      "SIT": 239.74,
      "SKK": 38.71,
      "CHF": 1.544,
      "ISK": 83.72,
      "NOK": 8.2435,
      "TRL": 1829000,
      "AUD": 1.7539,
      "CAD": 1.6483,
      "HKD": 10.5794,
      "KRW": 1417.06,
      "NZD": 1.9015,
      "SGD": 2.2285,
      "ZAR": 7.7064
    }
  },
  {
    "date": "2004-12-29",
    "base": "EUR",
    "rates": {
      "USD": 1.3608,
      "JPY": 140.76,
      "BGN": 1.9559,
      "CYP": 0.5796,
      "CZK": 30.495,
      "DKK": 7.4361,
      "EEK": 15.6466,
      "GBP": 0.7083,
      "HUF": 245.78,
      "LTL": 3.4528,
      "LVL": 0.6967,
      "MTL": 0.4346,
      "PLN": 4.065,
      "ROL": 39481,
      "SEK": 8.9883,
      "SIT": 239.74,
      "SKK": 38.793,
      "CHF": 1.5426,
      "ISK": 84.09,
      "NOK": 8.275,
      "TRL": 1849500,
      "AUD": 1.7477,
      "CAD": 1.6579,
      "HKD": 10.5861,
      "KRW": 1416.66,
      "NZD": 1.8897,
      "SGD": 2.2323,
      "ZAR": 7.6746
    }
  },
  {
    "date": "2004-12-28",
    "base": "EUR",
    "rates": {
      "USD": 1.3633,
      "JPY": 140.49,
      "BGN": 1.9559,
      "CYP": 0.5791,
      "CZK": 30.563,
      "DKK": 7.4409,
      "EEK": 15.6466,
      "GBP": 0.70315,
      "HUF": 245.88,
      "LTL": 3.4528,
      "LVL": 0.696,
      "MTL": 0.434,
      "PLN": 4.0527,
      "ROL": 39457,
      "SEK": 8.987,
      "SIT": 239.76,
      "SKK": 38.845,
      "CHF": 1.5441,
      "ISK": 84,
      "NOK": 8.272,
      "TRL": 1840700,
      "AUD": 1.7495,
      "CAD": 1.6562,
      "HKD": 10.5967,
      "KRW": 1421.17,
      "NZD": 1.8842,
      "SGD": 2.2272,
      "ZAR": 7.6666
    }
  },
  {
    "date": "2004-12-27",
    "base": "EUR",
    "rates": {
      "USD": 1.3527,
      "JPY": 140.34,
      "BGN": 1.9559,
      "CYP": 0.5786,
      "CZK": 30.555,
      "DKK": 7.4411,
      "EEK": 15.6466,
      "GBP": 0.7036,
      "HUF": 245.6,
      "LTL": 3.4528,
      "LVL": 0.6936,
      "MTL": 0.4338,
      "PLN": 4.0565,
      "ROL": 39648,
      "SEK": 9.0292,
      "SIT": 239.77,
      "SKK": 38.805,
      "CHF": 1.5484,
      "ISK": 83.78,
      "NOK": 8.265,
      "TRL": 1834938,
      "AUD": 1.7526,
      "CAD": 1.6625,
      "HKD": 10.5289,
      "KRW": 1415.8,
      "NZD": 1.8861,
      "SGD": 2.2186,
      "ZAR": 7.6495
    }
  },
  {
    "date": "2004-12-24",
    "base": "EUR",
    "rates": {
      "USD": 1.3542,
      "JPY": 140.26,
      "BGN": 1.9559,
      "CYP": 0.5787,
      "CZK": 30.433,
      "DKK": 7.4406,
      "EEK": 15.6466,
      "GBP": 0.7033,
      "HUF": 246.25,
      "LTL": 3.4528,
      "LVL": 0.6936,
      "MTL": 0.4337,
      "PLN": 4.0757,
      "ROL": 38700,
      "SEK": 9.035,
      "SIT": 239.78,
      "SKK": 38.83,
      "CHF": 1.5458,
      "ISK": 83.79,
      "NOK": 8.2815,
      "TRL": 1854638,
      "AUD": 1.7587,
      "CAD": 1.6631,
      "HKD": 10.5412,
      "KRW": 1419.13,
      "NZD": 1.8908,
      "SGD": 2.2203,
      "ZAR": 7.6377
    }
  },
  {
    "date": "2004-12-23",
    "base": "EUR",
    "rates": {
      "USD": 1.3456,
      "JPY": 139.88,
      "BGN": 1.9559,
      "CYP": 0.5789,
      "CZK": 30.6,
      "DKK": 7.4376,
      "EEK": 15.6466,
      "GBP": 0.7013,
      "HUF": 245.88,
      "LTL": 3.4528,
      "LVL": 0.6916,
      "MTL": 0.4332,
      "PLN": 4.072,
      "ROL": 38160,
      "SEK": 9.0275,
      "SIT": 239.79,
      "SKK": 38.81,
      "CHF": 1.5443,
      "ISK": 83.82,
      "NOK": 8.2825,
      "TRL": 1856190,
      "AUD": 1.758,
      "CAD": 1.6656,
      "HKD": 10.4706,
      "KRW": 1413.62,
      "NZD": 1.887,
      "SGD": 2.2048,
      "ZAR": 7.6
    }
  },
  {
    "date": "2004-12-22",
    "base": "EUR",
    "rates": {
      "USD": 1.3384,
      "JPY": 139.18,
      "BGN": 1.9559,
      "CYP": 0.5788,
      "CZK": 30.563,
      "DKK": 7.4351,
      "EEK": 15.6466,
      "GBP": 0.69905,
      "HUF": 245.71,
      "LTL": 3.4528,
      "LVL": 0.6895,
      "MTL": 0.4329,
      "PLN": 4.0908,
      "ROL": 37946,
      "SEK": 9.0245,
      "SIT": 239.73,
      "SKK": 38.75,
      "CHF": 1.5436,
      "ISK": 83.59,
      "NOK": 8.283,
      "TRL": 1860200,
      "AUD": 1.7442,
      "CAD": 1.6478,
      "HKD": 10.4143,
      "KRW": 1410.27,
      "NZD": 1.8735,
      "SGD": 2.194,
      "ZAR": 7.5985
    }
  },
  {
    "date": "2004-12-21",
    "base": "EUR",
    "rates": {
      "USD": 1.3394,
      "JPY": 139.85,
      "BGN": 1.9559,
      "CYP": 0.5788,
      "CZK": 30.493,
      "DKK": 7.4338,
      "EEK": 15.6466,
      "GBP": 0.6923,
      "HUF": 245.05,
      "LTL": 3.4528,
      "LVL": 0.6893,
      "MTL": 0.4322,
      "PLN": 4.1021,
      "ROL": 38551,
      "SEK": 8.9695,
      "SIT": 239.79,
      "SKK": 38.565,
      "CHF": 1.5403,
      "ISK": 83.75,
      "NOK": 8.2575,
      "TRL": 1862000,
      "AUD": 1.7476,
      "CAD": 1.6424,
      "HKD": 10.4202,
      "KRW": 1413.87,
      "NZD": 1.8779,
      "SGD": 2.1983,
      "ZAR": 7.5914
    }
  },
  {
    "date": "2004-12-20",
    "base": "EUR",
    "rates": {
      "USD": 1.3378,
      "JPY": 139.44,
      "BGN": 1.9559,
      "CYP": 0.5788,
      "CZK": 30.46,
      "DKK": 7.4329,
      "EEK": 15.6466,
      "GBP": 0.6874,
      "HUF": 244.93,
      "LTL": 3.4528,
      "LVL": 0.688,
      "MTL": 0.4315,
      "PLN": 4.1223,
      "ROL": 38672,
      "SEK": 8.963,
      "SIT": 239.78,
      "SKK": 38.545,
      "CHF": 1.5382,
      "ISK": 83.9,
      "NOK": 8.229,
      "TRL": 1855600,
      "AUD": 1.7516,
      "CAD": 1.6428,
      "HKD": 10.4076,
      "KRW": 1415.66,
      "NZD": 1.8672,
      "SGD": 2.1994,
      "ZAR": 7.6633
    }
  },
  {
    "date": "2004-12-17",
    "base": "EUR",
    "rates": {
      "USD": 1.3264,
      "JPY": 138.37,
      "BGN": 1.9559,
      "CYP": 0.5788,
      "CZK": 30.445,
      "DKK": 7.4318,
      "EEK": 15.6466,
      "GBP": 0.68585,
      "HUF": 245.58,
      "LTL": 3.4528,
      "LVL": 0.6849,
      "MTL": 0.4311,
      "PLN": 4.1465,
      "ROL": 38736,
      "SEK": 8.998,
      "SIT": 239.79,
      "SKK": 38.631,
      "CHF": 1.5367,
      "ISK": 84.09,
      "NOK": 8.217,
      "TRL": 1864100,
      "AUD": 1.7479,
      "CAD": 1.6351,
      "HKD": 10.3193,
      "KRW": 1406.12,
      "NZD": 1.8583,
      "SGD": 2.1843,
      "ZAR": 7.6747
    }
  },
  {
    "date": "2004-12-16",
    "base": "EUR",
    "rates": {
      "USD": 1.3401,
      "JPY": 138.93,
      "BGN": 1.9559,
      "CYP": 0.5788,
      "CZK": 30.62,
      "DKK": 7.4316,
      "EEK": 15.6466,
      "GBP": 0.6863,
      "HUF": 245.65,
      "LTL": 3.4528,
      "LVL": 0.6886,
      "MTL": 0.4315,
      "PLN": 4.1612,
      "ROL": 38403,
      "SEK": 8.9615,
      "SIT": 239.78,
      "SKK": 38.761,
      "CHF": 1.532,
      "ISK": 84.92,
      "NOK": 8.1855,
      "TRL": 1880100,
      "AUD": 1.7516,
      "CAD": 1.6436,
      "HKD": 10.4191,
      "KRW": 1415.82,
      "NZD": 1.8625,
      "SGD": 2.1973,
      "ZAR": 7.6824
    }
  },
  {
    "date": "2004-12-15",
    "base": "EUR",
    "rates": {
      "USD": 1.3383,
      "JPY": 139.51,
      "BGN": 1.9559,
      "CYP": 0.5788,
      "CZK": 30.608,
      "DKK": 7.434,
      "EEK": 15.6466,
      "GBP": 0.69115,
      "HUF": 245.75,
      "LTL": 3.4528,
      "LVL": 0.6891,
      "MTL": 0.432,
      "PLN": 4.1576,
      "ROL": 39197,
      "SEK": 8.9963,
      "SIT": 239.83,
      "SKK": 38.755,
      "CHF": 1.5282,
      "ISK": 84.74,
      "NOK": 8.226,
      "TRL": 1898100,
      "AUD": 1.7561,
      "CAD": 1.6479,
      "HKD": 10.4051,
      "KRW": 1420.07,
      "NZD": 1.8705,
      "SGD": 2.1954,
      "ZAR": 7.6875
    }
  },
  {
    "date": "2004-12-14",
    "base": "EUR",
    "rates": {
      "USD": 1.3317,
      "JPY": 139.7,
      "BGN": 1.9559,
      "CYP": 0.5788,
      "CZK": 30.608,
      "DKK": 7.433,
      "EEK": 15.6466,
      "GBP": 0.6915,
      "HUF": 246.58,
      "LTL": 3.4528,
      "LVL": 0.6883,
      "MTL": 0.4318,
      "PLN": 4.1786,
      "ROL": 39315,
      "SEK": 8.9573,
      "SIT": 239.76,
      "SKK": 38.785,
      "CHF": 1.5368,
      "ISK": 84.11,
      "NOK": 8.2,
      "TRL": 1893200,
      "AUD": 1.7494,
      "CAD": 1.6372,
      "HKD": 10.3538,
      "KRW": 1409.2,
      "NZD": 1.8668,
      "SGD": 2.1896,
      "ZAR": 7.6426
    }
  },
  {
    "date": "2004-12-13",
    "base": "EUR",
    "rates": {
      "USD": 1.3268,
      "JPY": 139.01,
      "BGN": 1.9559,
      "CYP": 0.5788,
      "CZK": 30.61,
      "DKK": 7.4303,
      "EEK": 15.6466,
      "GBP": 0.69225,
      "HUF": 247.21,
      "LTL": 3.4528,
      "LVL": 0.6869,
      "MTL": 0.4319,
      "PLN": 4.2021,
      "ROL": 39294,
      "SEK": 8.9675,
      "SIT": 239.84,
      "SKK": 38.945,
      "CHF": 1.5348,
      "ISK": 83.8,
      "NOK": 8.204,
      "TRL": 1898600,
      "AUD": 1.7505,
      "CAD": 1.6271,
      "HKD": 10.3166,
      "KRW": 1408.8,
      "NZD": 1.8674,
      "SGD": 2.1869,
      "ZAR": 7.6297
    }
  },
  {
    "date": "2004-12-10",
    "base": "EUR",
    "rates": {
      "USD": 1.3191,
      "JPY": 139.59,
      "BGN": 1.9559,
      "CYP": 0.5792,
      "CZK": 30.868,
      "DKK": 7.431,
      "EEK": 15.6466,
      "GBP": 0.6912,
      "HUF": 247.78,
      "LTL": 3.4528,
      "LVL": 0.686,
      "MTL": 0.4316,
      "PLN": 4.2077,
      "ROL": 38845,
      "SEK": 9.014,
      "SIT": 239.87,
      "SKK": 39.088,
      "CHF": 1.5349,
      "ISK": 83.62,
      "NOK": 8.218,
      "TRL": 1896000,
      "AUD": 1.7609,
      "CAD": 1.6225,
      "HKD": 10.2569,
      "KRW": 1408.01,
      "NZD": 1.8759,
      "SGD": 2.1884,
      "ZAR": 7.7072
    }
  },
  {
    "date": "2004-12-09",
    "base": "EUR",
    "rates": {
      "USD": 1.3305,
      "JPY": 139.17,
      "BGN": 1.9559,
      "CYP": 0.5792,
      "CZK": 30.784,
      "DKK": 7.4312,
      "EEK": 15.6466,
      "GBP": 0.6919,
      "HUF": 247.23,
      "LTL": 3.4528,
      "LVL": 0.6876,
      "MTL": 0.4319,
      "PLN": 4.1877,
      "ROL": 38392,
      "SEK": 8.994,
      "SIT": 239.86,
      "SKK": 39.073,
      "CHF": 1.5344,
      "ISK": 83.69,
      "NOK": 8.241,
      "TRL": 1912400,
      "AUD": 1.7639,
      "CAD": 1.6275,
      "HKD": 10.3484,
      "KRW": 1404.21,
      "NZD": 1.8794,
      "SGD": 2.1959,
      "ZAR": 7.8301
    }
  },
  {
    "date": "2004-12-08",
    "base": "EUR",
    "rates": {
      "USD": 1.33,
      "JPY": 138.63,
      "BGN": 1.9559,
      "CYP": 0.5792,
      "CZK": 30.884,
      "DKK": 7.4308,
      "EEK": 15.6466,
      "GBP": 0.6895,
      "HUF": 245.8,
      "LTL": 3.4528,
      "LVL": 0.6877,
      "MTL": 0.432,
      "PLN": 4.2055,
      "ROL": 38292,
      "SEK": 8.9627,
      "SIT": 239.87,
      "SKK": 39.097,
      "CHF": 1.533,
      "ISK": 82.2,
      "NOK": 8.2105,
      "TRL": 1881600,
      "AUD": 1.7586,
      "CAD": 1.6306,
      "HKD": 10.3343,
      "KRW": 1408.07,
      "NZD": 1.8823,
      "SGD": 2.1901,
      "ZAR": 7.7976
    }
  },
  {
    "date": "2004-12-07",
    "base": "EUR",
    "rates": {
      "USD": 1.3456,
      "JPY": 138.3,
      "BGN": 1.9559,
      "CYP": 0.5791,
      "CZK": 30.727,
      "DKK": 7.4292,
      "EEK": 15.6466,
      "GBP": 0.6906,
      "HUF": 245.74,
      "LTL": 3.4528,
      "LVL": 0.6898,
      "MTL": 0.4321,
      "PLN": 4.1743,
      "ROL": 38293,
      "SEK": 8.9065,
      "SIT": 239.86,
      "SKK": 39.093,
      "CHF": 1.5305,
      "ISK": 83.38,
      "NOK": 8.1355,
      "TRL": 1880900,
      "AUD": 1.7319,
      "CAD": 1.6074,
      "HKD": 10.4571,
      "KRW": 1401.98,
      "NZD": 1.8626,
      "SGD": 2.1993,
      "ZAR": 7.7176
    }
  },
  {
    "date": "2004-12-06",
    "base": "EUR",
    "rates": {
      "USD": 1.3435,
      "JPY": 137.47,
      "BGN": 1.9559,
      "CYP": 0.5791,
      "CZK": 30.786,
      "DKK": 7.4287,
      "EEK": 15.6466,
      "GBP": 0.6918,
      "HUF": 245.49,
      "LTL": 3.4528,
      "LVL": 0.689,
      "MTL": 0.4322,
      "PLN": 4.1707,
      "ROL": 38022,
      "SEK": 8.8992,
      "SIT": 239.84,
      "SKK": 39.135,
      "CHF": 1.5272,
      "ISK": 83.99,
      "NOK": 8.143,
      "TRL": 1878300,
      "AUD": 1.731,
      "CAD": 1.6072,
      "HKD": 10.4404,
      "KRW": 1398.38,
      "NZD": 1.8592,
      "SGD": 2.1955,
      "ZAR": 7.6784
    }
  },
  {
    "date": "2004-12-03",
    "base": "EUR",
    "rates": {
      "USD": 1.33,
      "JPY": 137.05,
      "BGN": 1.9559,
      "CYP": 0.5794,
      "CZK": 30.788,
      "DKK": 7.43,
      "EEK": 15.6466,
      "GBP": 0.6901,
      "HUF": 244.75,
      "LTL": 3.4528,
      "LVL": 0.6858,
      "MTL": 0.4317,
      "PLN": 4.1744,
      "ROL": 37209,
      "SEK": 8.951,
      "SIT": 239.81,
      "SKK": 39.054,
      "CHF": 1.5273,
      "ISK": 83.65,
      "NOK": 8.175,
      "TRL": 1882500,
      "AUD": 1.7204,
      "CAD": 1.5928,
      "HKD": 10.3378,
      "KRW": 1390.38,
      "NZD": 1.8579,
      "SGD": 2.18,
      "ZAR": 7.7592
    }
  },
  {
    "date": "2004-12-02",
    "base": "EUR",
    "rates": {
      "USD": 1.3314,
      "JPY": 136.78,
      "BGN": 1.9559,
      "CYP": 0.5795,
      "CZK": 30.895,
      "DKK": 7.4301,
      "EEK": 15.6466,
      "GBP": 0.68905,
      "HUF": 244.37,
      "LTL": 3.4528,
      "LVL": 0.6854,
      "MTL": 0.4316,
      "PLN": 4.173,
      "ROL": 38157,
      "SEK": 8.9755,
      "SIT": 239.79,
      "SKK": 39.025,
      "CHF": 1.5268,
      "ISK": 85.37,
      "NOK": 8.1665,
      "TRL": 1890700,
      "AUD": 1.7071,
      "CAD": 1.5739,
      "HKD": 10.3488,
      "KRW": 1386.65,
      "NZD": 1.8467,
      "SGD": 2.1771,
      "ZAR": 7.7357
    }
  },
  {
    "date": "2004-12-01",
    "base": "EUR",
    "rates": {
      "USD": 1.3294,
      "JPY": 136.83,
      "BGN": 1.9559,
      "CYP": 0.5794,
      "CZK": 30.984,
      "DKK": 7.4303,
      "EEK": 15.6466,
      "GBP": 0.69155,
      "HUF": 244.83,
      "LTL": 3.4528,
      "LVL": 0.6862,
      "MTL": 0.4318,
      "PLN": 4.1786,
      "ROL": 38378,
      "SEK": 8.9396,
      "SIT": 239.83,
      "SKK": 39.22,
      "CHF": 1.52,
      "ISK": 86.22,
      "NOK": 8.1295,
      "TRL": 1890400,
      "AUD": 1.7236,
      "CAD": 1.5845,
      "HKD": 10.3365,
      "KRW": 1390.69,
      "NZD": 1.8604,
      "SGD": 2.1749,
      "ZAR": 7.7288
    }
  }
]