[
  {
    "date": "2010-10-29",
    "base": "EUR",
    "rates": {
      "USD": 1.3857,
      "JPY": 111.87,
      "BGN": 1.9558,
      "CZK": 24.598,
      "DKK": 7.4562,
      "EEK": 15.6466,
      "GBP": 0.8686,
      "HUF": 271.76,
      "LTL": 3.4528,
      "LVL": 0.7097,
      "PLN": 3.982,
      "RON": 4.2663,
      "SEK": 9.361,
      "CHF": 1.3708,
      "NOK": 8.192,
      "HRK": 7.347,
      "RUB": 42.7523,
      "TRY": 1.9887,
      "AUD": 1.4216,
      "BRL": 2.3638,
      "CAD": 1.415,
      "CNY": 9.2437,
      "HKD": 10.7467,
      "IDR": 12383.89,
      "INR": 61.52,
      "KRW": 1557.9,
      "MXN": 17.1544,
      "MYR": 4.309,
      "NZD": 1.828,
      "PHP": 59.741,
      "SGD": 1.7968,
      "THB": 41.509,
      "ZAR": 9.6827
    }
  },
  {
    "date": "2010-10-28",
    "base": "EUR",
    "rates": {
      "USD": 1.3857,
      "JPY": 112.57,
      "BGN": 1.9558,
      "CZK": 24.63,
      "DKK": 7.4584,
      "EEK": 15.6466,
      "GBP": 0.8704,
      "HUF": 273.25,
      "LTL": 3.4528,
      "LVL": 0.7098,
      "PLN": 3.9646,
      "RON": 4.2698,
      "SEK": 9.3164,
      "CHF": 1.3668,
      "NOK": 8.15,
      "HRK": 7.3422,
      "RUB": 42.55,
      "TRY": 1.9869,
      "AUD": 1.4158,
      "BRL": 2.3742,
      "CAD": 1.4195,
      "CNY": 9.2667,
      "HKD": 10.7501,
      "IDR": 12382.71,
      "INR": 61.67,
      "KRW": 1557.32,
      "MXN": 17.1935,
      "MYR": 4.3088,
      "NZD": 1.8459,
      "PHP": 59.726,
      "SGD": 1.7994,
      "THB": 41.516,
      "ZAR": 9.7451
    }
  },
  {
    "date": "2010-10-27",
    "base": "EUR",
    "rates": {
      "USD": 1.3803,
      "JPY": 112.78,
      "BGN": 1.9558,
      "CZK": 24.663,
      "DKK": 7.4585,
      "EEK": 15.6466,
      "GBP": 0.87235,
      "HUF": 275.04,
      "LTL": 3.4528,
      "LVL": 0.7093,
      "PLN": 3.9501,
      "RON": 4.2762,
      "SEK": 9.3317,
      "CHF": 1.3639,
      "NOK": 8.145,
      "HRK": 7.3452,
      "RUB": 42.3172,
      "TRY": 1.9834,
      "AUD": 1.4194,
      "BRL": 2.3546,
      "CAD": 1.421,
      "CNY": 9.2212,
      "HKD": 10.7096,
      "IDR": 12340.46,
      "INR": 61.472,
      "KRW": 1561.75,
      "MXN": 17.1847,
      "MYR": 4.296,
      "NZD": 1.85,
      "PHP": 59.646,
      "SGD": 1.7974,
      "THB": 41.402,
      "ZAR": 9.712
    }
  },
  {
    "date": "2010-10-26",
    "base": "EUR",
    "rates": {
      "USD": 1.3912,
      "JPY": 113.11,
      "BGN": 1.9558,
      "CZK": 24.618,
      "DKK": 7.4577,
      "EEK": 15.6466,
      "GBP": 0.87685,
      "HUF": 274.6,
      "LTL": 3.4528,
      "LVL": 0.7097,
      "PLN": 3.9352,
      "RON": 4.275,
      "SEK": 9.3028,
      "CHF": 1.3558,
      "NOK": 8.12,
      "HRK": 7.3423,
      "RUB": 42.2875,
      "TRY": 1.9785,
      "AUD": 1.4108,
      "BRL": 2.3674,
      "CAD": 1.4245,
      "CNY": 9.2691,
      "HKD": 10.7925,
      "IDR": 12410.75,
      "INR": 61.985,
      "KRW": 1558.32,
      "MXN": 17.2473,
      "MYR": 4.3079,
      "NZD": 1.8549,
      "PHP": 60.064,
      "SGD": 1.8053,
      "THB": 41.611,
      "ZAR": 9.634
    }
  },
  {
    "date": "2010-10-25",
    "base": "EUR",
    "rates": {
      "USD": 1.4031,
      "JPY": 113.21,
      "BGN": 1.9558,
      "CZK": 24.51,
      "DKK": 7.4579,
      "EEK": 15.6466,
      "GBP": 0.89255,
      "HUF": 273.53,
      "LTL": 3.4528,
      "LVL": 0.7095,
      "PLN": 3.9316,
      "RON": 4.268,
      "SEK": 9.199,
      "CHF": 1.3618,
      "NOK": 8.0935,
      "HRK": 7.3413,
      "RUB": 42.4705,
      "TRY": 1.9845,
      "AUD": 1.4107,
      "BRL": 2.3889,
      "CAD": 1.4291,
      "CNY": 9.342,
      "HKD": 10.8887,
      "IDR": 12485.42,
      "INR": 62.24,
      "KRW": 1565.89,
      "MXN": 17.2332,
      "MYR": 4.3405,
      "NZD": 1.8623,
      "PHP": 60.347,
      "SGD": 1.812,
      "THB": 41.883,
      "ZAR": 9.6931
    }
  },
  {
    "date": "2010-10-22",
    "base": "EUR",
    "rates": {
      "USD": 1.3934,
      "JPY": 113.18,
      "BGN": 1.9558,
      "CZK": 24.626,
      "DKK": 7.4577,
      "EEK": 15.6466,
      "GBP": 0.8873,
      "HUF": 275.35,
      "LTL": 3.4528,
      "LVL": 0.7097,
      "PLN": 3.9701,
      "RON": 4.3013,
      "SEK": 9.2565,
      "CHF": 1.3533,
      "NOK": 8.143,
      "HRK": 7.3365,
      "RUB": 42.4507,
      "TRY": 1.9896,
      "AUD": 1.4198,
      "BRL": 2.3594,
      "CAD": 1.4299,
      "CNY": 9.2787,
      "HKD": 10.8203,
      "IDR": 12457.54,
      "INR": 62.103,
      "KRW": 1571.8,
      "MXN": 17.242,
      "MYR": 4.339,
      "NZD": 1.8636,
      "PHP": 60.375,
      "SGD": 1.8137,
      "THB": 41.722,
      "ZAR": 9.6876
    }
  },
  {
    "date": "2010-10-21",
    "base": "EUR",
    "rates": {
      "USD": 1.4016,
      "JPY": 113.65,
      "BGN": 1.9558,
      "CZK": 24.54,
      "DKK": 7.4584,
      "EEK": 15.6466,
      "GBP": 0.8902,
      "HUF": 274.5,
      "LTL": 3.4528,
      "LVL": 0.7098,
      "PLN": 3.9516,
      "RON": 4.3152,
      "SEK": 9.2675,
      "CHF": 1.3493,
      "NOK": 8.1385,
      "HRK": 7.3405,
      "RUB": 43.0028,
      "TRY": 1.9907,
      "AUD": 1.4208,
      "BRL": 2.3517,
      "CAD": 1.43,
      "CNY": 9.3212,
      "HKD": 10.8813,
      "IDR": 12520.42,
      "INR": 62.084,
      "KRW": 1576.39,
      "MXN": 17.3126,
      "MYR": 4.3534,
      "NZD": 1.8637,
      "PHP": 60.552,
      "SGD": 1.8192,
      "THB": 41.859,
      "ZAR": 9.6623
    }
  },
  {
    "date": "2010-10-20",
    "base": "EUR",
    "rates": {
      "USD": 1.3861,
      "JPY": 112.59,
      "BGN": 1.9558,
      "CZK": 24.503,
      "DKK": 7.4581,
      "EEK": 15.6466,
      "GBP": 0.882,
      "HUF": 275.58,
      "LTL": 3.4528,
      "LVL": 0.7095,
      "PLN": 3.9593,
      "RON": 4.3068,
      "SEK": 9.3115,
      "CHF": 1.3355,
      "NOK": 8.1585,
      "HRK": 7.332,
      "RUB": 42.695,
      "TRY": 1.9811,
      "AUD": 1.4151,
      "BRL": 2.32,
      "CAD": 1.426,
      "CNY": 9.2202,
      "HKD": 10.7604,
      "IDR": 12389.96,
      "INR": 61.501,
      "KRW": 1566.02,
      "MXN": 17.2757,
      "MYR": 4.3267,
      "NZD": 1.8489,
      "PHP": 60.149,
      "SGD": 1.8116,
      "THB": 41.486,
      "ZAR": 9.628
    }
  },
  {
    "date": "2010-10-19",
    "base": "EUR",
    "rates": {
      "USD": 1.3859,
      "JPY": 113.16,
      "BGN": 1.9558,
      "CZK": 24.52,
      "DKK": 7.4574,
      "EEK": 15.6466,
      "GBP": 0.8806,
      "HUF": 276.89,
      "LTL": 3.4528,
      "LVL": 0.7099,
      "PLN": 3.9363,
      "RON": 4.298,
      "SEK": 9.335,
      "CHF": 1.3405,
      "NOK": 8.169,
      "HRK": 7.3295,
      "RUB": 42.29,
      "TRY": 1.9775,
      "AUD": 1.4159,
      "BRL": 2.3387,
      "CAD": 1.4217,
      "CNY": 9.2089,
      "HKD": 10.7531,
      "IDR": 12386.04,
      "INR": 61.543,
      "KRW": 1561.31,
      "MXN": 17.2607,
      "MYR": 4.3081,
      "NZD": 1.8491,
      "PHP": 60.121,
      "SGD": 1.8126,
      "THB": 41.452,
      "ZAR": 9.6507
    }
  },
  {
    "date": "2010-10-18",
    "base": "EUR",
    "rates": {
      "USD": 1.3896,
      "JPY": 113,
      "BGN": 1.9558,
      "CZK": 24.536,
      "DKK": 7.4575,
      "EEK": 15.6466,
      "GBP": 0.8747,
      "HUF": 276.63,
      "LTL": 3.4528,
      "LVL": 0.7092,
      "PLN": 3.9226,
      "RON": 4.2815,
      "SEK": 9.2871,
      "CHF": 1.3359,
      "NOK": 8.15,
      "HRK": 7.337,
      "RUB": 42.3575,
      "TRY": 1.9748,
      "AUD": 1.4087,
      "BRL": 2.3271,
      "CAD": 1.4192,
      "CNY": 9.2326,
      "HKD": 10.7812,
      "IDR": 12412.48,
      "INR": 61.675,
      "KRW": 1553.51,
      "MXN": 17.3713,
      "MYR": 4.3036,
      "NZD": 1.8442,
      "PHP": 60.142,
      "SGD": 1.8091,
      "THB": 41.546,
      "ZAR": 9.57
    }
  },
  {
    "date": "2010-10-15",
    "base": "EUR",
    "rates": {
      "USD": 1.4089,
      "JPY": 114.28,
      "BGN": 1.9558,
      "CZK": 24.515,
      "DKK": 7.4564,
      "EEK": 15.6466,
      "GBP": 0.8775,
      "HUF": 274.18,
      "LTL": 3.4528,
      "LVL": 0.7097,
      "PLN": 3.905,
      "RON": 4.2765,
      "SEK": 9.223,
      "CHF": 1.3423,
      "NOK": 8.0925,
      "HRK": 7.3355,
      "RUB": 42.565,
      "TRY": 1.9808,
      "AUD": 1.4142,
      "BRL": 2.3369,
      "CAD": 1.4165,
      "CNY": 9.3568,
      "HKD": 10.93,
      "IDR": 12530.82,
      "INR": 62.132,
      "KRW": 1564.64,
      "MXN": 17.458,
      "MYR": 4.3443,
      "NZD": 1.8565,
      "PHP": 60.847,
      "SGD": 1.8244,
      "THB": 42.015,
      "ZAR": 9.5833
    }
  },
  {
    "date": "2010-10-14",
    "base": "EUR",
    "rates": {
      "USD": 1.4101,
      "JPY": 114.43,
      "BGN": 1.9558,
      "CZK": 24.44,
      "DKK": 7.4571,
      "EEK": 15.6466,
      "GBP": 0.8792,
      "HUF": 273.63,
      "LTL": 3.4528,
      "LVL": 0.7095,
      "PLN": 3.9077,
      "RON": 4.2799,
      "SEK": 9.234,
      "CHF": 1.3386,
      "NOK": 8.0695,
      "HRK": 7.3275,
      "RUB": 42.3188,
      "TRY": 1.9762,
      "AUD": 1.4145,
      "BRL": 2.3213,
      "CAD": 1.4088,
      "CNY": 9.3783,
      "HKD": 10.9419,
      "IDR": 12574.79,
      "INR": 62.214,
      "KRW": 1564.26,
      "MXN": 17.4022,
      "MYR": 4.3473,
      "NZD": 1.8538,
      "PHP": 60.944,
      "SGD": 1.8248,
      "THB": 42.014,
      "ZAR": 9.5642
    }
  },
  {
    "date": "2010-10-13",
    "base": "EUR",
    "rates": {
      "USD": 1.3958,
      "JPY": 114.23,
      "BGN": 1.9558,
      "CZK": 24.47,
      "DKK": 7.4565,
      "EEK": 15.6466,
      "GBP": 0.8812,
      "HUF": 273.45,
      "LTL": 3.4528,
      "LVL": 0.7095,
      "PLN": 3.9545,
      "RON": 4.2773,
      "SEK": 9.2662,
      "CHF": 1.3352,
      "NOK": 8.135,
      "HRK": 7.3308,
      "RUB": 42.0055,
      "TRY": 1.9723,
      "AUD": 1.4128,
      "BRL": 2.324,
      "CAD": 1.3999,
      "CNY": 9.3018,
      "HKD": 10.8317,
      "IDR": 12461.72,
      "INR": 62.08,
      "KRW": 1564.83,
      "MXN": 17.29,
      "MYR": 4.3172,
      "NZD": 1.8407,
      "PHP": 60.733,
      "SGD": 1.8181,
      "THB": 41.79,
      "ZAR": 9.5766
    }
  },
  {
    "date": "2010-10-12",
    "base": "EUR",
    "rates": {
      "USD": 1.3833,
      "JPY": 113.35,
      "BGN": 1.9558,
      "CZK": 24.524,
      "DKK": 7.4569,
      "EEK": 15.6466,
      "GBP": 0.8736,
      "HUF": 273.85,
      "LTL": 3.4528,
      "LVL": 0.7091,
      "PLN": 3.964,
      "RON": 4.2743,
      "SEK": 9.246,
      "CHF": 1.3298,
      "NOK": 8.124,
      "HRK": 7.3247,
      "RUB": 41.68,
      "TRY": 1.9659,
      "AUD": 1.4076,
      "BRL": 2.3106,
      "CAD": 1.4023,
      "CNY": 9.2313,
      "HKD": 10.735,
      "IDR": 12365.2,
      "INR": 61.7846,
      "KRW": 1561.58,
      "MXN": 17.2359,
      "MYR": 4.3,
      "NZD": 1.8334,
      "PHP": 60.477,
      "SGD": 1.8083,
      "THB": 41.437,
      "ZAR": 9.5572
    }
  },
  {
    "date": "2010-10-11",
    "base": "EUR",
    "rates": {
      "USD": 1.3936,
      "JPY": 114.24,
      "BGN": 1.9558,
      "CZK": 24.542,
      "DKK": 7.4577,
      "EEK": 15.6466,
      "GBP": 0.8746,
      "HUF": 274.03,
      "LTL": 3.4528,
      "LVL": 0.709,
      "PLN": 3.9605,
      "RON": 4.2668,
      "SEK": 9.2715,
      "CHF": 1.3412,
      "NOK": 8.1235,
      "HRK": 7.3203,
      "RUB": 41.575,
      "TRY": 1.968,
      "AUD": 1.4153,
      "BRL": 2.3198,
      "CAD": 1.41,
      "CNY": 9.2922,
      "HKD": 10.8131,
      "IDR": 12439.09,
      "INR": 61.932,
      "KRW": 1560.69,
      "MXN": 17.2861,
      "MYR": 4.3223,
      "NZD": 1.8523,
      "PHP": 60.605,
      "SGD": 1.8197,
      "THB": 41.857,
      "ZAR": 9.6019
    }
  },
  {
    "date": "2010-10-08",
    "base": "EUR",
    "rates": {
      "USD": 1.3874,
      "JPY": 114.21,
      "BGN": 1.9558,
      "CZK": 24.49,
      "DKK": 7.4562,
      "EEK": 15.6466,
      "GBP": 0.8751,
      "HUF": 275.55,
      "LTL": 3.4528,
      "LVL": 0.7091,
      "PLN": 3.9765,
      "RON": 4.2643,
      "SEK": 9.317,
      "CHF": 1.342,
      "NOK": 8.1,
      "HRK": 7.3173,
      "RUB": 41.593,
      "TRY": 1.9782,
      "AUD": 1.4252,
      "BRL": 2.3394,
      "CAD": 1.4168,
      "CNY": 9.2548,
      "HKD": 10.7641,
      "IDR": 12393.04,
      "INR": 61.635,
      "KRW": 1565.97,
      "MXN": 17.4337,
      "MYR": 4.322,
      "NZD": 1.8598,
      "PHP": 60.328,
      "SGD": 1.8198,
      "THB": 41.709,
      "ZAR": 9.5991
    }
  },
  {
    "date": "2010-10-07",
    "base": "EUR",
    "rates": {
      "USD": 1.397,
      "JPY": 115.1,
      "BGN": 1.9558,
      "CZK": 24.518,
      "DKK": 7.4561,
      "EEK": 15.6466,
      "GBP": 0.87465,
      "HUF": 273.33,
      "LTL": 3.4528,
      "LVL": 0.709,
      "PLN": 3.9655,
      "RON": 4.2648,
      "SEK": 9.3208,
      "CHF": 1.3415,
      "NOK": 8.083,
      "HRK": 7.3188,
      "RUB": 41.5745,
      "TRY": 1.9823,
      "AUD": 1.4132,
      "BRL": 2.339,
      "CAD": 1.412,
      "CNY": 9.3298,
      "HKD": 10.8333,
      "IDR": 12467.7,
      "INR": 61.7684,
      "KRW": 1558.32,
      "MXN": 17.4122,
      "MYR": 4.3195,
      "NZD": 1.8445,
      "PHP": 60.67,
      "SGD": 1.8246,
      "THB": 41.714,
      "ZAR": 9.6183
    }
  },
  {
    "date": "2010-10-06",
    "base": "EUR",
    "rates": {
      "USD": 1.3856,
      "JPY": 114.98,
      "BGN": 1.9558,
      "CZK": 24.53,
      "DKK": 7.4547,
      "EEK": 15.6466,
      "GBP": 0.8726,
      "HUF": 270.33,
      "LTL": 3.4528,
      "LVL": 0.7091,
      "PLN": 3.949,
      "RON": 4.272,
      "SEK": 9.2993,
      "CHF": 1.3361,
      "NOK": 8.034,
      "HRK": 7.3145,
      "RUB": 41.36,
      "TRY": 1.965,
      "AUD": 1.4221,
      "BRL": 2.3113,
      "CAD": 1.4018,
      "CNY": 9.2713,
      "HKD": 10.7471,
      "IDR": 12357.62,
      "INR": 61.5,
      "KRW": 1550.99,
      "MXN": 17.2854,
      "MYR": 4.287,
      "NZD": 1.8423,
      "PHP": 60.275,
      "SGD": 1.8155,
      "THB": 41.492,
      "ZAR": 9.5445
    }
  },
  {
    "date": "2010-10-05",
    "base": "EUR",
    "rates": {
      "USD": 1.378,
      "JPY": 114.8,
      "BGN": 1.9558,
      "CZK": 24.498,
      "DKK": 7.4549,
      "EEK": 15.6466,
      "GBP": 0.8667,
      "HUF": 272.73,
      "LTL": 3.4528,
      "LVL": 0.7092,
      "PLN": 3.9708,
      "RON": 4.278,
      "SEK": 9.2626,
      "CHF": 1.3348,
      "NOK": 8.041,
      "HRK": 7.3048,
      "RUB": 41.64,
      "TRY": 1.9889,
      "AUD": 1.4338,
      "BRL": 2.334,
      "CAD": 1.407,
      "CNY": 9.2205,
      "HKD": 10.6886,
      "IDR": 12310.68,
      "INR": 61.555,
      "KRW": 1557.45,
      "MXN": 17.2951,
      "MYR": 4.267,
      "NZD": 1.8515,
      "PHP": 60.27,
      "SGD": 1.8083,
      "THB": 41.533,
      "ZAR": 9.5759
    }
  },
  {
    "date": "2010-10-04",
    "base": "EUR",
    "rates": {
      "USD": 1.3705,
      "JPY": 114.1,
      "BGN": 1.9558,
      "CZK": 24.469,
      "DKK": 7.4541,
      "EEK": 15.6466,
      "GBP": 0.8656,
      "HUF": 272.22,
      "LTL": 3.4528,
      "LVL": 0.7092,
      "PLN": 3.9483,
      "RON": 4.2759,
      "SEK": 9.2398,
      "CHF": 1.3327,
      "NOK": 8.03,
      "HRK": 7.292,
      "RUB": 41.8045,
      "TRY": 1.9817,
      "AUD": 1.4153,
      "BRL": 2.3078,
      "CAD": 1.3998,
      "CNY": 9.1703,
      "HKD": 10.6334,
      "IDR": 12248.04,
      "INR": 61.063,
      "KRW": 1541.35,
      "MXN": 17.2053,
      "MYR": 4.2376,
      "NZD": 1.8456,
      "PHP": 59.916,
      "SGD": 1.8005,
      "THB": 41.341,
      "ZAR": 9.548
    }
  },
  {
    "date": "2010-10-01",
    "base": "EUR",
    "rates": {
      "USD": 1.3726,
      "JPY": 114.26,
      "BGN": 1.9558,
      "CZK": 24.42,
      "DKK": 7.4523,
      "EEK": 15.6466,
      "GBP": 0.8676,
      "HUF": 273.85,
      "LTL": 3.4528,
      "LVL": 0.7092,
      "PLN": 3.937,
      "RON": 4.2655,
      "SEK": 9.2183,
      "CHF": 1.3423,
      "NOK": 8.04,
      "HRK": 7.3018,
      "RUB": 41.8,
      "TRY": 1.9856,
      "AUD": 1.4114,
      "BRL": 2.3036,
      "CAD": 1.4085,
      "CNY": 9.1843,
      "HKD": 10.6511,
      "IDR": 12232,
      "INR": 61.081,
      "KRW": 1546.1,
      "MXN": 17.1947,
      "MYR": 4.2352,
      "NZD": 1.855,
      "PHP": 60.066,
      "SGD": 1.8016,
      "THB": 41.463,
      "ZAR": 9.5121
    }
  }
]