[
  {
    "date": "2025-02-28",
    "base": "EUR",
    "rates": {
      "USD": 1.0411,
      "JPY": 156.96,
      "BGN": 1.9558,
      "CZK": 25.029,
      "DKK": 7.4583,
      "GBP": 0.82608,
      "HUF": 399.5,
      "PLN": 4.1503,
      "RON": 4.9768,
      "SEK": 11.188,
      "CHF": 0.9394,
      "ISK": 145.7,
      "NOK": 11.7245,
      "TRY": 38.0186,
      "AUD": 1.6741,
      "BRL": 6.0712,
      "CAD": 1.5019,
      "CNY": 7.5782,
      "HKD": 8.098,
      "IDR": 17228.17,
      "ILS": 3.7457,
      "INR": 90.971,
      "KRW": 1519.92,
      "MXN": 21.2191,
      "MYR": 4.6459,
      "NZD": 1.8579,
      "PHP": 60.355,
      "SGD": 1.4037,
      "THB": 35.567,
      "ZAR": 19.1917
    }
  },
  {
    "date": "2025-02-27",
    "base": "EUR",
    "rates": {
      "USD": 1.0477,
      "JPY": 156.73,
      "BGN": 1.9558,
      "CZK": 24.987,
      "DKK": 7.4584,
      "GBP": 0.82673,
      "HUF": 399.43,
      "PLN": 4.1308,
      "RON": 4.9763,
      "SEK": 11.159,
      "CHF": 0.9407,
      "ISK": 145.5,
      "NOK": 11.7015,
      "TRY": 38.1682,
      "AUD": 1.6638,
      "BRL": 6.0825,
      "CAD": 1.504,
      "CNY": 7.6127,
      "HKD": 8.1446,
      "IDR": 17238.38,
      "ILS": 3.7184,
      "INR": 91.311,
      "KRW": 1511.87,
      "MXN": 21.3501,
      "MYR": 4.6565,
      "NZD": 1.8434,
      "PHP": 60.632,
      "SGD": 1.4049,
      "THB": 35.522,
      "ZAR": 19.2947
    }
  },
  {
    "date": "2025-02-26",
    "base": "EUR",
    "rates": {
      "USD": 1.0487,
      "JPY": 156.7,
      "BGN": 1.9558,
      "CZK": 24.948,
      "DKK": 7.4584,
      "GBP": 0.82868,
      "HUF": 400.3,
      "PLN": 4.144,
      "RON": 4.9773,
      "SEK": 11.143,
      "CHF": 0.9392,
      "ISK": 145.3,
      "NOK": 11.6895,
      "TRY": 38.2126,
      "AUD": 1.6622,
      "BRL": 6.0329,
      "CAD": 1.5054,
      "CNY": 7.6125,
      "HKD": 8.1516,
      "IDR": 17171.68,
      "ILS": 3.7475,
      "INR": 91.3495,
      "KRW": 1504.35,
      "MXN": 21.4685,
      "MYR": 4.6447,
      "NZD": 1.8419,
      "PHP": 60.733,
      "SGD": 1.4035,
      "THB": 35.388,
      "ZAR": 19.2857
    }
  },
  {
    "date": "2025-02-25",
    "base": "EUR",
    "rates": {
      "USD": 1.0497,
      "JPY": 157.19,
      "BGN": 1.9558,
      "CZK": 24.939,
      "DKK": 7.4595,
      "GBP": 0.82908,
      "HUF": 401.2,
      "PLN": 4.1393,
      "RON": 4.9774,
      "SEK": 11.1455,
      "CHF": 0.9386,
      "ISK": 145.7,
      "NOK": 11.6638,
      "TRY": 38.2742,
      "AUD": 1.6538,
      "BRL": 6.0839,
      "CAD": 1.4969,
      "CNY": 7.6219,
      "HKD": 8.1609,
      "IDR": 17160.65,
      "ILS": 3.7569,
      "INR": 91.5198,
      "KRW": 1505.11,
      "MXN": 21.494,
      "MYR": 4.6449,
      "NZD": 1.8337,
      "PHP": 60.832,
      "SGD": 1.4047,
      "THB": 35.38,
      "ZAR": 19.2862
    }
  },
  {
    "date": "2025-02-24",
    "base": "EUR",
    "rates": {
      "USD": 1.0466,
      "JPY": 156.81,
      "BGN": 1.9558,
      "CZK": 25.062,
      "DKK": 7.4603,
      "GBP": 0.8283,
      "HUF": 401.69,
      "PLN": 4.1445,
      "RON": 4.9772,
      "SEK": 11.153,
      "CHF": 0.9415,
      "ISK": 145.1,
      "NOK": 11.6355,
      "TRY": 38.0941,
      "AUD": 1.6434,
      "BRL": 5.9857,
      "CAD": 1.4876,
      "CNY": 7.5879,
      "HKD": 8.1356,
      "IDR": 17044.56,
      "ILS": 3.7334,
      "INR": 90.7663,
      "KRW": 1494.52,
      "MXN": 21.3703,
      "MYR": 4.616,
      "NZD": 1.8213,
      "PHP": 60.581,
      "SGD": 1.4002,
      "THB": 35.066,
      "ZAR": 19.2037
    }
  },
  {
    "date": "2025-02-21",
    "base": "EUR",
    "rates": {
      "USD": 1.0465,
      "JPY": 157.46,
      "BGN": 1.9558,
      "CZK": 25.082,
      "DKK": 7.4588,
      "GBP": 0.8276,
      "HUF": 404.6,
      "PLN": 4.1683,
      "RON": 4.9773,
      "SEK": 11.1425,
      "CHF": 0.942,
      "ISK": 145.7,
      "NOK": 11.629,
      "TRY": 38.1023,
      "AUD": 1.6394,
      "BRL": 5.9751,
      "CAD": 1.4856,
      "CNY": 7.5933,
      "HKD": 8.1327,
      "IDR": 17077.52,
      "ILS": 3.7211,
      "INR": 90.6598,
      "KRW": 1500.16,
      "MXN": 21.2714,
      "MYR": 4.624,
      "NZD": 1.8186,
      "PHP": 60.64,
      "SGD": 1.3994,
      "THB": 35.183,
      "ZAR": 19.245
    }
  },
  {
    "date": "2025-02-20",
    "base": "EUR",
    "rates": {
      "USD": 1.0443,
      "JPY": 156.6,
      "BGN": 1.9558,
      "CZK": 25.073,
      "DKK": 7.459,
      "GBP": 0.82823,
      "HUF": 402.08,
      "PLN": 4.1605,
      "RON": 4.9778,
      "SEK": 11.166,
      "CHF": 0.9423,
      "ISK": 145.7,
      "NOK": 11.609,
      "TRY": 37.9226,
      "AUD": 1.6382,
      "BRL": 5.9526,
      "CAD": 1.4841,
      "CNY": 7.5807,
      "HKD": 8.1211,
      "IDR": 17011.8,
      "ILS": 3.6986,
      "INR": 90.426,
      "KRW": 1500.62,
      "MXN": 21.2619,
      "MYR": 4.6262,
      "NZD": 1.8227,
      "PHP": 60.462,
      "SGD": 1.3966,
      "THB": 35.099,
      "ZAR": 19.248
    }
  },
  {
    "date": "2025-02-19",
    "base": "EUR",
    "rates": {
      "USD": 1.0434,
      "JPY": 158.41,
      "BGN": 1.9558,
      "CZK": 25.101,
      "DKK": 7.4588,
      "GBP": 0.82838,
      "HUF": 402.13,
      "PLN": 4.174,
      "RON": 4.9774,
      "SEK": 11.214,
      "CHF": 0.9435,
      "ISK": 146.3,
      "NOK": 11.629,
      "TRY": 37.8746,
      "AUD": 1.6419,
      "BRL": 5.9775,
      "CAD": 1.4821,
      "CNY": 7.6017,
      "HKD": 8.1148,
      "IDR": 17081.19,
      "ILS": 3.6976,
      "INR": 90.642,
      "KRW": 1504.72,
      "MXN": 21.1954,
      "MYR": 4.6343,
      "NZD": 1.8252,
      "PHP": 60.651,
      "SGD": 1.4008,
      "THB": 35.157,
      "ZAR": 19.3298
    }
  },
  {
    "date": "2025-02-18",
    "base": "EUR",
    "rates": {
      "USD": 1.0447,
      "JPY": 158.55,
      "BGN": 1.9558,
      "CZK": 25.098,
      "DKK": 7.4582,
      "GBP": 0.83025,
      "HUF": 401.54,
      "PLN": 4.166,
      "RON": 4.9773,
      "SEK": 11.2115,
      "CHF": 0.9425,
      "ISK": 146.7,
      "NOK": 11.659,
      "TRY": 37.8958,
      "AUD": 1.6466,
      "BRL": 5.9576,
      "CAD": 1.4844,
      "CNY": 7.6056,
      "HKD": 8.1235,
      "IDR": 17067.58,
      "ILS": 3.7177,
      "INR": 90.85,
      "KRW": 1506.32,
      "MXN": 21.1919,
      "MYR": 4.6442,
      "NZD": 1.8338,
      "PHP": 60.846,
      "SGD": 1.4036,
      "THB": 35.222,
      "ZAR": 19.2608
    }
  },
  {
    "date": "2025-02-17",
    "base": "EUR",
    "rates": {
      "USD": 1.0473,
      "JPY": 158.67,
      "BGN": 1.9558,
      "CZK": 25.056,
      "DKK": 7.4597,
      "GBP": 0.83133,
      "HUF": 401.73,
      "PLN": 4.1605,
      "RON": 4.977,
      "SEK": 11.216,
      "CHF": 0.944,
      "ISK": 146.9,
      "NOK": 11.6415,
      "TRY": 37.9484,
      "AUD": 1.6456,
      "BRL": 5.9756,
      "CAD": 1.4861,
      "CNY": 7.6066,
      "HKD": 8.1481,
      "IDR": 16993.02,
      "ILS": 3.7239,
      "INR": 90.992,
      "KRW": 1511.85,
      "MXN": 21.351,
      "MYR": 4.6437,
      "NZD": 1.8263,
      "PHP": 60.757,
      "SGD": 1.405,
      "THB": 35.31,
      "ZAR": 19.3112
    }
  },
  {
    "date": "2025-02-14",
    "base": "EUR",
    "rates": {
      "USD": 1.0478,
      "JPY": 160.09,
      "BGN": 1.9558,
      "CZK": 25.043,
      "DKK": 7.459,
      "GBP": 0.83215,
      "HUF": 402.95,
      "PLN": 4.1653,
      "RON": 4.977,
      "SEK": 11.2445,
      "CHF": 0.9442,
      "ISK": 147.3,
      "NOK": 11.6515,
      "TRY": 37.9486,
      "AUD": 1.6514,
      "BRL": 6.0127,
      "CAD": 1.4856,
      "CNY": 7.6141,
      "HKD": 8.1554,
      "IDR": 16980.33,
      "ILS": 3.7341,
      "INR": 90.81,
      "KRW": 1509.5,
      "MXN": 21.3146,
      "MYR": 4.647,
      "NZD": 1.8352,
      "PHP": 60.487,
      "SGD": 1.4052,
      "THB": 35.238,
      "ZAR": 19.2555
    }
  },
  {
    "date": "2025-02-13",
    "base": "EUR",
    "rates": {
      "USD": 1.039,
      "JPY": 159.79,
      "BGN": 1.9558,
      "CZK": 25.057,
      "DKK": 7.4586,
      "GBP": 0.83313,
      "HUF": 401.78,
      "PLN": 4.1688,
      "RON": 4.9771,
      "SEK": 11.2815,
      "CHF": 0.9421,
      "ISK": 146.8,
      "NOK": 11.7145,
      "TRY": 37.515,
      "AUD": 1.6591,
      "BRL": 6.0084,
      "CAD": 1.4844,
      "CNY": 7.5817,
      "HKD": 8.0926,
      "IDR": 17024.53,
      "ILS": 3.7162,
      "INR": 90.3771,
      "KRW": 1507.52,
      "MXN": 21.4383,
      "MYR": 4.6287,
      "NZD": 1.8447,
      "PHP": 60.312,
      "SGD": 1.4033,
      "THB": 35.227,
      "ZAR": 19.2471
    }
  },
  {
    "date": "2025-02-12",
    "base": "EUR",
    "rates": {
      "USD": 1.037,
      "JPY": 159.22,
      "BGN": 1.9558,
      "CZK": 25.075,
      "DKK": 7.4583,
      "GBP": 0.83338,
      "HUF": 402.63,
      "PLN": 4.1713,
      "RON": 4.9767,
      "SEK": 11.2895,
      "CHF": 0.9457,
      "ISK": 146.4,
      "NOK": 11.662,
      "TRY": 37.4321,
      "AUD": 1.6525,
      "BRL": 5.9812,
      "CAD": 1.483,
      "CNY": 7.5794,
      "HKD": 8.0769,
      "IDR": 16953.65,
      "ILS": 3.7259,
      "INR": 90.101,
      "KRW": 1505.97,
      "MXN": 21.3163,
      "MYR": 4.6354,
      "NZD": 1.8391,
      "PHP": 60.291,
      "SGD": 1.4031,
      "THB": 35.367,
      "ZAR": 19.1398
    }
  },
  {
    "date": "2025-02-11",
    "base": "EUR",
    "rates": {
      "USD": 1.0324,
      "JPY": 157.28,
      "BGN": 1.9558,
      "CZK": 25.101,
      "DKK": 7.4582,
      "GBP": 0.83355,
      "HUF": 403.9,
      "PLN": 4.1785,
      "RON": 4.9769,
      "SEK": 11.2525,
      "CHF": 0.9429,
      "ISK": 146.6,
      "NOK": 11.5755,
      "TRY": 37.22,
      "AUD": 1.6442,
      "BRL": 5.9898,
      "CAD": 1.4789,
      "CNY": 7.544,
      "HKD": 8.0452,
      "IDR": 16897.29,
      "ILS": 3.7088,
      "INR": 89.548,
      "KRW": 1500.7,
      "MXN": 21.2848,
      "MYR": 4.6148,
      "NZD": 1.8284,
      "PHP": 60.05,
      "SGD": 1.3995,
      "THB": 35.22,
      "ZAR": 19.0894
    }
  },
  {
    "date": "2025-02-10",
    "base": "EUR",
    "rates": {
      "USD": 1.032,
      "JPY": 156.92,
      "BGN": 1.9558,
      "CZK": 25.073,
      "DKK": 7.4584,
      "GBP": 0.83283,
      "HUF": 403.88,
      "PLN": 4.1758,
      "RON": 4.9769,
      "SEK": 11.2765,
      "CHF": 0.9396,
      "ISK": 146.6,
      "NOK": 11.5745,
      "TRY": 37.1484,
      "AUD": 1.6448,
      "BRL": 5.9622,
      "CAD": 1.4798,
      "CNY": 7.5395,
      "HKD": 8.04,
      "IDR": 16867.63,
      "ILS": 3.679,
      "INR": 90.274,
      "KRW": 1496.81,
      "MXN": 21.2378,
      "MYR": 4.613,
      "NZD": 1.8257,
      "PHP": 60.011,
      "SGD": 1.3972,
      "THB": 34.993,
      "ZAR": 19.0069
    }
  },
  {
    "date": "2025-02-07",
    "base": "EUR",
    "rates": {
      "USD": 1.0377,
      "JPY": 157.77,
      "BGN": 1.9558,
      "CZK": 25.108,
      "DKK": 7.46,
      "GBP": 0.83353,
      "HUF": 405.55,
      "PLN": 4.1985,
      "RON": 4.9768,
      "SEK": 11.2865,
      "CHF": 0.9418,
      "ISK": 146.6,
      "NOK": 11.625,
      "TRY": 37.3344,
      "AUD": 1.6525,
      "BRL": 5.9857,
      "CAD": 1.4883,
      "CNY": 7.5634,
      "HKD": 8.0828,
      "IDR": 16933.08,
      "ILS": 3.6872,
      "INR": 90.8135,
      "KRW": 1501.65,
      "MXN": 21.2827,
      "MYR": 4.6074,
      "NZD": 1.8287,
      "PHP": 60.19,
      "SGD": 1.4021,
      "THB": 34.924,
      "ZAR": 19.1225
    }
  },
  {
    "date": "2025-02-06",
    "base": "EUR",
    "rates": {
      "USD": 1.036,
      "JPY": 157.95,
      "BGN": 1.9558,
      "CZK": 25.139,
      "DKK": 7.4596,
      "GBP": 0.83688,
      "HUF": 406.1,
      "PLN": 4.2065,
      "RON": 4.9767,
      "SEK": 11.321,
      "CHF": 0.9385,
      "ISK": 146.6,
      "NOK": 11.6585,
      "TRY": 37.1866,
      "AUD": 1.6547,
      "BRL": 6.0127,
      "CAD": 1.4865,
      "CNY": 7.5511,
      "HKD": 8.0668,
      "IDR": 16943.78,
      "ILS": 3.6892,
      "INR": 90.76,
      "KRW": 1502.98,
      "MXN": 21.3713,
      "MYR": 4.5947,
      "NZD": 1.8317,
      "PHP": 60.202,
      "SGD": 1.4027,
      "THB": 35.053,
      "ZAR": 19.2822
    }
  },
  {
    "date": "2025-02-05",
    "base": "EUR",
    "rates": {
      "USD": 1.0422,
      "JPY": 159.25,
      "BGN": 1.9558,
      "CZK": 25.136,
      "DKK": 7.4597,
      "GBP": 0.83085,
      "HUF": 406,
      "PLN": 4.1968,
      "RON": 4.9766,
      "SEK": 11.3583,
      "CHF": 0.9395,
      "ISK": 146.8,
      "NOK": 11.6693,
      "TRY": 37.4306,
      "AUD": 1.658,
      "BRL": 6.0327,
      "CAD": 1.4876,
      "CNY": 7.5797,
      "HKD": 8.1162,
      "IDR": 17003.7,
      "ILS": 3.7012,
      "INR": 91.0595,
      "KRW": 1507.59,
      "MXN": 21.4775,
      "MYR": 4.6091,
      "NZD": 1.8321,
      "PHP": 60.44,
      "SGD": 1.4053,
      "THB": 34.987,
      "ZAR": 19.3507
    }
  },
  {
    "date": "2025-02-04",
    "base": "EUR",
    "rates": {
      "USD": 1.0335,
      "JPY": 160.52,
      "BGN": 1.9558,
      "CZK": 25.172,
      "DKK": 7.461,
      "GBP": 0.83188,
      "HUF": 407.15,
      "PLN": 4.2193,
      "RON": 4.9769,
      "SEK": 11.418,
      "CHF": 0.9396,
      "ISK": 146.8,
      "NOK": 11.721,
      "TRY": 37.1554,
      "AUD": 1.6629,
      "BRL": 6.0138,
      "CAD": 1.4894,
      "CNY": 7.4943,
      "HKD": 8.0489,
      "IDR": 16865.27,
      "ILS": 3.6961,
      "INR": 90.011,
      "KRW": 1504.21,
      "MXN": 21.1322,
      "MYR": 4.5929,
      "NZD": 1.8418,
      "PHP": 60.222,
      "SGD": 1.4015,
      "THB": 34.937,
      "ZAR": 19.4072
    }
  },
  {
    "date": "2025-02-03",
    "base": "EUR",
    "rates": {
      "USD": 1.0274,
      "JPY": 158.87,
      "BGN": 1.9558,
      "CZK": 25.254,
      "DKK": 7.4618,
      "GBP": 0.83136,
      "HUF": 408.43,
      "PLN": 4.2255,
      "RON": 4.9769,
      "SEK": 11.481,
      "CHF": 0.9393,
      "ISK": 146,
      "NOK": 11.7138,
      "TRY": 36.9718,
      "AUD": 1.6671,
      "BRL": 6.0119,
      "CAD": 1.5051,
      "CNY": 7.45,
      "HKD": 8.0072,
      "IDR": 16864.57,
      "ILS": 3.6992,
      "INR": 89.4513,
      "KRW": 1504.01,
      "MXN": 21.5073,
      "MYR": 4.5976,
      "NZD": 1.8424,
      "PHP": 60.158,
      "SGD": 1.4024,
      "THB": 34.932,
      "ZAR": 19.3445
    }
  }
]