[
  {
    "date": "2026-02-02",
    "base": "EUR",
    "rates": {
      "USD": 1.184,
      "JPY": 183.59,
      "CZK": 24.305,
      "DKK": 7.4691,
      "GBP": 0.8658,
      "HUF": 381.2,
      "PLN": 4.2173,
      "RON": 5.096,
      "SEK": 10.5935,
      "CHF": 0.9199,
      "ISK": 145,
      "NOK": 11.4655,
      "TRY": 51.4941,
      "AUD": 1.7042,
      "BRL": 6.2222,
      "CAD": 1.6157,
      "CNY": 8.221,
      "HKD": 9.2484,
      "IDR": 19890,
      "ILS": 3.6738,
      "INR": 108.417,
      "KRW": 1719.74,
      "MXN": 20.6131,
      "MYR": 4.6673,
      "NZD": 1.9705,
      "PHP": 69.754,
      "SGD": 1.5055,
      "THB": 37.432,
      "ZAR": 18.9774
    }
  }
]