{
  "date": "2025-11-28",
  "base": "EUR",
  "rates": {
    "USD": 1.1566,
    "JPY": 180.57,
    "BGN": 1.9558,
    "CZK": 24.177,
    "DKK": 7.4688,
    "GBP": 0.8752,
    "HUF": 381.43,
    "PLN": 4.239,
    "RON": 5.0909,
    "SEK": 10.9695,
    "CHF": 0.9318,
    "ISK": 148.2,
    "NOK": 11.7645,
    "TRY": 49.1509,
    "AUD": 1.7721,
    "BRL": 6.1752,
    "CAD": 1.621,
    "CNY": 8.1836,
    "HKD": 9.002,
    "IDR": 19269.07,
    "ILS": 3.7705,
    "INR": 103.4905,
    "KRW": 1699.81,
    "MXN": 21.2168,
    "MYR": 4.7796,
    "NZD": 2.0247,
    "PHP": 67.853,
    "SGD": 1.5008,
    "THB": 37.237,
    "ZAR": 19.7962
  }
}