[
  {
    "date": "2004-03-31",
    "base": "EUR",
    "rates": {
      "USD": 1.2224,
      "JPY": 126.97,
      "BGN": 1.9464,
      "CYP": 0.5862,
      "CZK": 32.833,
      "DKK": 7.4448,
      "EEK": 15.6466,
      "GBP": 0.6659,
      "HUF": 249.25,
      "LTL": 3.4529,
      "LVL": 0.654,
      "MTL": 0.4258,
      "PLN": 4.7336,
      "ROL": 40963,
      "SEK": 9.2581,
      "SIT": 238.38,
      "SKK": 40.115,
      "CHF": 1.5594,
      "ISK": 88.27,
      "NOK": 8.436,
      "TRL": 1612187,
      "AUD": 1.6052,
      "CAD": 1.5979,
      "HKD": 9.5228,
      "KRW": 1401.42,
      "NZD": 1.8365,
      "SGD": 2.0459,
      "ZAR": 7.7788
    }
  },
  {
    "date": "2004-03-30",
    "base": "EUR",
    "rates": {
      "USD": 1.2187,
      "JPY": 128.99,
      "BGN": 1.9462,
      "CYP": 0.58617,
      "CZK": 32.983,
      "DKK": 7.4447,
      "EEK": 15.6466,
      "GBP": 0.6681,
      "HUF": 249.85,
      "LTL": 3.4529,
      "LVL": 0.6549,
      "MTL": 0.4261,
      "PLN": 4.7298,
      "ROL": 40442,
      "SEK": 9.2596,
      "SIT": 238.4,
      "SKK": 40.18,
      "CHF": 1.5586,
      "ISK": 88.45,
      "NOK": 8.4085,
      "TRL": 1609898,
      "AUD": 1.6179,
      "CAD": 1.5922,
      "HKD": 9.5012,
      "KRW": 1405.59,
      "NZD": 1.8544,
      "SGD": 2.0523,
      "ZAR": 7.6105
    }
  },
  {
    "date": "2004-03-29",
    "base": "EUR",
    "rates": {
      "USD": 1.2118,
      "JPY": 128.13,
      "BGN": 1.9461,
      "CYP": 0.58617,
      "CZK": 32.808,
      "DKK": 7.445,
      "EEK": 15.6466,
      "GBP": 0.6674,
      "HUF": 250.45,
      "LTL": 3.4529,
      "LVL": 0.6526,
      "MTL": 0.4258,
      "PLN": 4.7175,
      "ROL": 40478,
      "SEK": 9.2665,
      "SIT": 238.15,
      "SKK": 40.195,
      "CHF": 1.5583,
      "ISK": 87.92,
      "NOK": 8.4525,
      "TRL": 1600513,
      "AUD": 1.6285,
      "CAD": 1.5985,
      "HKD": 9.4473,
      "KRW": 1398.96,
      "NZD": 1.8673,
      "SGD": 2.0477,
      "ZAR": 7.7738
    }
  },
  {
    "date": "2004-03-26",
    "base": "EUR",
    "rates": {
      "USD": 1.2173,
      "JPY": 128.59,
      "BGN": 1.9462,
      "CYP": 0.58617,
      "CZK": 32.729,
      "DKK": 7.4472,
      "EEK": 15.6466,
      "GBP": 0.66985,
      "HUF": 251.06,
      "LTL": 3.4526,
      "LVL": 0.6546,
      "MTL": 0.4262,
      "PLN": 4.7489,
      "ROL": 40281,
      "SEK": 9.2665,
      "SIT": 238.17,
      "SKK": 40.23,
      "CHF": 1.556,
      "ISK": 87.51,
      "NOK": 8.446,
      "TRL": 1607394,
      "AUD": 1.6314,
      "CAD": 1.6106,
      "HKD": 9.4922,
      "KRW": 1409.21,
      "NZD": 1.8705,
      "SGD": 2.0564,
      "ZAR": 8.0243
    }
  },
  {
    "date": "2004-03-25",
    "base": "EUR",
    "rates": {
      "USD": 1.2132,
      "JPY": 128.72,
      "BGN": 1.9462,
      "CYP": 0.58617,
      "CZK": 32.62,
      "DKK": 7.4466,
      "EEK": 15.6466,
      "GBP": 0.6725,
      "HUF": 251.02,
      "LTL": 3.4527,
      "LVL": 0.6542,
      "MTL": 0.4264,
      "PLN": 4.7126,
      "ROL": 40093,
      "SEK": 9.281,
      "SIT": 238.16,
      "SKK": 40.235,
      "CHF": 1.5505,
      "ISK": 87.52,
      "NOK": 8.458,
      "TRL": 1607766,
      "AUD": 1.6404,
      "CAD": 1.6283,
      "HKD": 9.4591,
      "KRW": 1403.98,
      "NZD": 1.8756,
      "SGD": 2.0539,
      "ZAR": 8.0204
    }
  },
  {
    "date": "2004-03-24",
    "base": "EUR",
    "rates": {
      "USD": 1.2196,
      "JPY": 129.76,
      "BGN": 1.9461,
      "CYP": 0.58617,
      "CZK": 32.725,
      "DKK": 7.4474,
      "EEK": 15.6466,
      "GBP": 0.6653,
      "HUF": 251.07,
      "LTL": 3.453,
      "LVL": 0.6552,
      "MTL": 0.4257,
      "PLN": 4.6991,
      "ROL": 40074,
      "SEK": 9.2414,
      "SIT": 238.1,
      "SKK": 40.145,
      "CHF": 1.5533,
      "ISK": 87.99,
      "NOK": 8.429,
      "TRL": 1609822,
      "AUD": 1.6337,
      "CAD": 1.6307,
      "HKD": 9.507,
      "KRW": 1408.33,
      "NZD": 1.8723,
      "SGD": 2.0601,
      "ZAR": 8.015
    }
  },
  {
    "date": "2004-03-23",
    "base": "EUR",
    "rates": {
      "USD": 1.2276,
      "JPY": 131.17,
      "BGN": 1.9463,
      "CYP": 0.5861,
      "CZK": 33.13,
      "DKK": 7.4473,
      "EEK": 15.6466,
      "GBP": 0.6664,
      "HUF": 251.9,
      "LTL": 3.4527,
      "LVL": 0.6579,
      "MTL": 0.426,
      "PLN": 4.699,
      "ROL": 39977,
      "SEK": 9.2272,
      "SIT": 238.08,
      "SKK": 40.165,
      "CHF": 1.5524,
      "ISK": 88.46,
      "NOK": 8.432,
      "TRL": 1623143,
      "AUD": 1.6355,
      "CAD": 1.6364,
      "HKD": 9.5689,
      "KRW": 1419.29,
      "NZD": 1.8611,
      "SGD": 2.0738,
      "ZAR": 8.0215
    }
  },
  {
    "date": "2004-03-22",
    "base": "EUR",
    "rates": {
      "USD": 1.2353,
      "JPY": 132.17,
      "BGN": 1.9465,
      "CYP": 0.58606,
      "CZK": 33.171,
      "DKK": 7.4469,
      "EEK": 15.6466,
      "GBP": 0.66945,
      "HUF": 253.2,
      "LTL": 3.4529,
      "LVL": 0.6606,
      "MTL": 0.4266,
      "PLN": 4.7318,
      "ROL": 40083,
      "SEK": 9.2185,
      "SIT": 238.03,
      "SKK": 40.255,
      "CHF": 1.5574,
      "ISK": 87.6,
      "NOK": 8.429,
      "TRL": 1630333,
      "AUD": 1.643,
      "CAD": 1.6407,
      "HKD": 9.6263,
      "KRW": 1433.57,
      "NZD": 1.8659,
      "SGD": 2.0881,
      "ZAR": 8.1701
    }
  },
  {
    "date": "2004-03-19",
    "base": "EUR",
    "rates": {
      "USD": 1.2344,
      "JPY": 132,
      "BGN": 1.9466,
      "CYP": 0.58599,
      "CZK": 33.21,
      "DKK": 7.447,
      "EEK": 15.6466,
      "GBP": 0.6735,
      "HUF": 253.56,
      "LTL": 3.4533,
      "LVL": 0.6608,
      "MTL": 0.4271,
      "PLN": 4.72,
      "ROL": 40030,
      "SEK": 9.2713,
      "SIT": 238.04,
      "SKK": 40.375,
      "CHF": 1.5587,
      "ISK": 87.24,
      "NOK": 8.515,
      "TRL": 1623482,
      "AUD": 1.6499,
      "CAD": 1.6428,
      "HKD": 9.6189,
      "KRW": 1429.44,
      "NZD": 1.8841,
      "SGD": 2.0879,
      "ZAR": 8.1995
    }
  },
  {
    "date": "2004-03-18",
    "base": "EUR",
    "rates": {
      "USD": 1.2261,
      "JPY": 131.22,
      "BGN": 1.9464,
      "CYP": 0.58599,
      "CZK": 33.153,
      "DKK": 7.4474,
      "EEK": 15.6466,
      "GBP": 0.67215,
      "HUF": 254.45,
      "LTL": 3.4533,
      "LVL": 0.6584,
      "MTL": 0.4268,
      "PLN": 4.7366,
      "ROL": 39955,
      "SEK": 9.2493,
      "SIT": 238.02,
      "SKK": 40.41,
      "CHF": 1.5625,
      "ISK": 86.97,
      "NOK": 8.502,
      "TRL": 1627981,
      "AUD": 1.6522,
      "CAD": 1.6414,
      "HKD": 9.5547,
      "KRW": 1422.09,
      "NZD": 1.8828,
      "SGD": 2.0727,
      "ZAR": 8.1894
    }
  },
  {
    "date": "2004-03-17",
    "base": "EUR",
    "rates": {
      "USD": 1.2251,
      "JPY": 132.75,
      "BGN": 1.9462,
      "CYP": 0.58599,
      "CZK": 33.185,
      "DKK": 7.4482,
      "EEK": 15.6466,
      "GBP": 0.6756,
      "HUF": 254.95,
      "LTL": 3.4533,
      "LVL": 0.6596,
      "MTL": 0.4271,
      "PLN": 4.7303,
      "ROL": 39927,
      "SEK": 9.2438,
      "SIT": 237.98,
      "SKK": 40.455,
      "CHF": 1.567,
      "ISK": 86.69,
      "NOK": 8.462,
      "TRL": 1620129,
      "AUD": 1.6576,
      "CAD": 1.6367,
      "HKD": 9.5451,
      "KRW": 1426.2,
      "NZD": 1.8904,
      "SGD": 2.0817,
      "ZAR": 8.2584
    }
  },
  {
    "date": "2004-03-16",
    "base": "EUR",
    "rates": {
      "USD": 1.235,
      "JPY": 135,
      "BGN": 1.9462,
      "CYP": 0.58593,
      "CZK": 33.198,
      "DKK": 7.4497,
      "EEK": 15.6466,
      "GBP": 0.6792,
      "HUF": 255,
      "LTL": 3.4529,
      "LVL": 0.6635,
      "MTL": 0.4278,
      "PLN": 4.7325,
      "ROL": 39955,
      "SEK": 9.238,
      "SIT": 238.06,
      "SKK": 40.46,
      "CHF": 1.5692,
      "ISK": 86.6,
      "NOK": 8.479,
      "TRL": 1628084,
      "AUD": 1.6656,
      "CAD": 1.643,
      "HKD": 9.623,
      "KRW": 1445.88,
      "NZD": 1.896,
      "SGD": 2.1013,
      "ZAR": 8.2511
    }
  },
  {
    "date": "2004-03-15",
    "base": "EUR",
    "rates": {
      "USD": 1.2278,
      "JPY": 136.02,
      "BGN": 1.9463,
      "CYP": 0.58589,
      "CZK": 33.165,
      "DKK": 7.4515,
      "EEK": 15.6466,
      "GBP": 0.6818,
      "HUF": 253.83,
      "LTL": 3.452,
      "LVL": 0.6632,
      "MTL": 0.4279,
      "PLN": 4.7229,
      "ROL": 39895,
      "SEK": 9.2563,
      "SIT": 238.02,
      "SKK": 40.456,
      "CHF": 1.5645,
      "ISK": 86.6,
      "NOK": 8.4895,
      "TRL": 1615435,
      "AUD": 1.6727,
      "CAD": 1.6353,
      "HKD": 9.5693,
      "KRW": 1442.97,
      "NZD": 1.9044,
      "SGD": 2.0979,
      "ZAR": 8.2566
    }
  },
  {
    "date": "2004-03-12",
    "base": "EUR",
    "rates": {
      "USD": 1.2235,
      "JPY": 136.15,
      "BGN": 1.9461,
      "CYP": 0.58579,
      "CZK": 33.074,
      "DKK": 7.4517,
      "EEK": 15.6466,
      "GBP": 0.6814,
      "HUF": 253.85,
      "LTL": 3.4524,
      "LVL": 0.6625,
      "MTL": 0.4278,
      "PLN": 4.7648,
      "ROL": 39919,
      "SEK": 9.2376,
      "SIT": 238,
      "SKK": 40.494,
      "CHF": 1.5692,
      "ISK": 86.72,
      "NOK": 8.56,
      "TRL": 1614822,
      "AUD": 1.6748,
      "CAD": 1.6306,
      "HKD": 9.5368,
      "KRW": 1444.65,
      "NZD": 1.8964,
      "SGD": 2.0973,
      "ZAR": 8.2703
    }
  },
  {
    "date": "2004-03-11",
    "base": "EUR",
    "rates": {
      "USD": 1.2256,
      "JPY": 135.58,
      "BGN": 1.9462,
      "CYP": 0.58575,
      "CZK": 33.145,
      "DKK": 7.4518,
      "EEK": 15.6466,
      "GBP": 0.6792,
      "HUF": 252.55,
      "LTL": 3.4524,
      "LVL": 0.6622,
      "MTL": 0.4276,
      "PLN": 4.7794,
      "ROL": 39881,
      "SEK": 9.207,
      "SIT": 238.05,
      "SKK": 40.535,
      "CHF": 1.567,
      "ISK": 86.55,
      "NOK": 8.584,
      "TRL": 1624301,
      "AUD": 1.663,
      "CAD": 1.6215,
      "HKD": 9.5537,
      "KRW": 1432.67,
      "NZD": 1.8896,
      "SGD": 2.0985,
      "ZAR": 8.2441
    }
  },
  {
    "date": "2004-03-10",
    "base": "EUR",
    "rates": {
      "USD": 1.2299,
      "JPY": 136.36,
      "BGN": 1.9461,
      "CYP": 0.58586,
      "CZK": 33.199,
      "DKK": 7.4522,
      "EEK": 15.6466,
      "GBP": 0.6756,
      "HUF": 253.56,
      "LTL": 3.4524,
      "LVL": 0.6628,
      "MTL": 0.4273,
      "PLN": 4.7676,
      "ROL": 39867,
      "SEK": 9.1748,
      "SIT": 238.04,
      "SKK": 40.55,
      "CHF": 1.5758,
      "ISK": 86.56,
      "NOK": 8.656,
      "TRL": 1620987,
      "AUD": 1.6384,
      "CAD": 1.6262,
      "HKD": 9.5842,
      "KRW": 1442.37,
      "NZD": 1.8445,
      "SGD": 2.1031,
      "ZAR": 8.0938
    }
  },
  {
    "date": "2004-03-09",
    "base": "EUR",
    "rates": {
      "USD": 1.2361,
      "JPY": 137.7,
      "BGN": 1.9461,
      "CYP": 0.58589,
      "CZK": 33.057,
      "DKK": 7.4523,
      "EEK": 15.6466,
      "GBP": 0.6721,
      "HUF": 253.85,
      "LTL": 3.4526,
      "LVL": 0.6645,
      "MTL": 0.4271,
      "PLN": 4.7728,
      "ROL": 39952,
      "SEK": 9.1653,
      "SIT": 238,
      "SKK": 40.555,
      "CHF": 1.5801,
      "ISK": 86.62,
      "NOK": 8.644,
      "TRL": 1627564,
      "AUD": 1.6242,
      "CAD": 1.6398,
      "HKD": 9.6297,
      "KRW": 1452.36,
      "NZD": 1.8163,
      "SGD": 2.1071,
      "ZAR": 8.192
    }
  },
  {
    "date": "2004-03-08",
    "base": "EUR",
    "rates": {
      "USD": 1.2356,
      "JPY": 138.6,
      "BGN": 1.9463,
      "CYP": 0.58589,
      "CZK": 33.085,
      "DKK": 7.4519,
      "EEK": 15.6466,
      "GBP": 0.6678,
      "HUF": 254.05,
      "LTL": 3.4528,
      "LVL": 0.6646,
      "MTL": 0.4264,
      "PLN": 4.8076,
      "ROL": 39850,
      "SEK": 9.1652,
      "SIT": 238.07,
      "SKK": 40.565,
      "CHF": 1.5822,
      "ISK": 87.05,
      "NOK": 8.651,
      "TRL": 1632846,
      "AUD": 1.6322,
      "CAD": 1.636,
      "HKD": 9.6269,
      "KRW": 1449.91,
      "NZD": 1.8291,
      "SGD": 2.1133,
      "ZAR": 8.1608
    }
  },
  {
    "date": "2004-03-05",
    "base": "EUR",
    "rates": {
      "USD": 1.2192,
      "JPY": 135.5,
      "BGN": 1.9469,
      "CYP": 0.58589,
      "CZK": 33.115,
      "DKK": 7.4519,
      "EEK": 15.6466,
      "GBP": 0.6704,
      "HUF": 256.22,
      "LTL": 3.4529,
      "LVL": 0.6594,
      "MTL": 0.4263,
      "PLN": 4.8436,
      "ROL": 39881,
      "SEK": 9.2,
      "SIT": 237.96,
      "SKK": 40.645,
      "CHF": 1.5778,
      "ISK": 87.21,
      "NOK": 8.665,
      "TRL": 1615109,
      "AUD": 1.625,
      "CAD": 1.6276,
      "HKD": 9.492,
      "KRW": 1429.88,
      "NZD": 1.8223,
      "SGD": 2.0909,
      "ZAR": 8.3147
    }
  },
  {
    "date": "2004-03-04",
    "base": "EUR",
    "rates": {
      "USD": 1.2147,
      "JPY": 134.43,
      "BGN": 1.9473,
      "CYP": 0.58589,
      "CZK": 33.035,
      "DKK": 7.4522,
      "EEK": 15.6466,
      "GBP": 0.6663,
      "HUF": 254.35,
      "LTL": 3.4529,
      "LVL": 0.6578,
      "MTL": 0.4257,
      "PLN": 4.8126,
      "ROL": 39899,
      "SEK": 9.2151,
      "SIT": 237.93,
      "SKK": 40.685,
      "CHF": 1.5793,
      "ISK": 86.88,
      "NOK": 8.6365,
      "TRL": 1613577,
      "AUD": 1.6178,
      "CAD": 1.629,
      "HKD": 9.4661,
      "KRW": 1421.38,
      "NZD": 1.8125,
      "SGD": 2.0844,
      "ZAR": 8.31
    }
  },
  {
    "date": "2004-03-03",
    "base": "EUR",
    "rates": {
      "USD": 1.2143,
      "JPY": 133.81,
      "BGN": 1.9478,
      "CYP": 0.58589,
      "CZK": 32.921,
      "DKK": 7.4519,
      "EEK": 15.6466,
      "GBP": 0.6633,
      "HUF": 256.38,
      "LTL": 3.4529,
      "LVL": 0.6569,
      "MTL": 0.4253,
      "PLN": 4.8441,
      "ROL": 39775,
      "SEK": 9.255,
      "SIT": 237.98,
      "SKK": 40.575,
      "CHF": 1.5807,
      "ISK": 86.89,
      "NOK": 8.6985,
      "TRL": 1619737,
      "AUD": 1.6192,
      "CAD": 1.6443,
      "HKD": 9.4614,
      "KRW": 1429.41,
      "NZD": 1.8152,
      "SGD": 2.078,
      "ZAR": 8.3909
    }
  },
  {
    "date": "2004-03-02",
    "base": "EUR",
    "rates": {
      "USD": 1.2402,
      "JPY": 135.98,
      "BGN": 1.9477,
      "CYP": 0.58589,
      "CZK": 32.66,
      "DKK": 7.4524,
      "EEK": 15.6466,
      "GBP": 0.667,
      "HUF": 255.95,
      "LTL": 3.4525,
      "LVL": 0.6639,
      "MTL": 0.4265,
      "PLN": 4.8758,
      "ROL": 39767,
      "SEK": 9.2481,
      "SIT": 237.99,
      "SKK": 40.458,
      "CHF": 1.5838,
      "ISK": 87.24,
      "NOK": 8.685,
      "TRL": 1636775,
      "AUD": 1.6071,
      "CAD": 1.6618,
      "HKD": 9.655,
      "KRW": 1455.44,
      "NZD": 1.7985,
      "SGD": 2.1138,
      "ZAR": 8.2283
    }
  },
  {
    "date": "2004-03-01",
    "base": "EUR",
    "rates": {
      "USD": 1.2484,
      "JPY": 136.28,
      "BGN": 1.9477,
      "CYP": 0.58589,
      "CZK": 32.465,
      "DKK": 7.452,
      "EEK": 15.6466,
      "GBP": 0.6683,
      "HUF": 256.3,
      "LTL": 3.4525,
      "LVL": 0.6658,
      "MTL": 0.4268,
      "PLN": 4.8944,
      "ROL": 39733,
      "SEK": 9.251,
      "SIT": 237.96,
      "SKK": 40.468,
      "CHF": 1.5783,
      "ISK": 86.8,
      "NOK": 8.717,
      "TRL": 1646706,
      "AUD": 1.6148,
      "CAD": 1.6707,
      "HKD": 9.7174,
      "KRW": 1471.24,
      "NZD": 1.8164,
      "SGD": 2.1219,
      "ZAR": 8.2766
    }
  }
]