[
  {
    "date": "2012-03-30",
    "base": "EUR",
    "rates": {
      "USD": 1.3356,
      "JPY": 109.56,
      "BGN": 1.9558,
      "CZK": 24.73,
      "DKK": 7.4399,
      "GBP": 0.8339,
      "HUF": 294.92,
      "LTL": 3.4528,
      "LVL": 0.7003,
      "PLN": 4.1522,
      "RON": 4.382,
      "SEK": 8.8455,
      "CHF": 1.2045,
      "NOK": 7.604,
      "HRK": 7.5125,
      "RUB": 39.295,
      "TRY": 2.3774,
      "AUD": 1.2836,
      "BRL": 2.4323,
      "CAD": 1.3311,
      "CNY": 8.4089,
      "HKD": 10.3705,
      "IDR": 12245.24,
      "ILS": 4.957,
      "INR": 68.042,
      "KRW": 1512.98,
      "MXN": 17.0222,
      "MYR": 4.0916,
      "NZD": 1.6254,
      "PHP": 57.281,
      "SGD": 1.6775,
      "THB": 41.177,
      "ZAR": 10.2322
    }
  },
  {
    "date": "2012-03-29",
    "base": "EUR",
    "rates": {
      "USD": 1.3272,
      "JPY": 109.21,
      "BGN": 1.9558,
      "CZK": 24.778,
      "DKK": 7.4372,
      "GBP": 0.8358,
      "HUF": 294.36,
      "LTL": 3.4528,
      "LVL": 0.7007,
      "PLN": 4.1612,
      "RON": 4.3807,
      "SEK": 8.845,
      "CHF": 1.2051,
      "NOK": 7.632,
      "HRK": 7.5108,
      "RUB": 38.96,
      "TRY": 2.3677,
      "AUD": 1.283,
      "BRL": 2.4315,
      "CAD": 1.3271,
      "CNY": 8.3652,
      "HKD": 10.3048,
      "IDR": 12164.39,
      "ILS": 4.9586,
      "INR": 68.112,
      "KRW": 1509.85,
      "MXN": 16.9975,
      "MYR": 4.0738,
      "NZD": 1.6292,
      "PHP": 57.139,
      "SGD": 1.6705,
      "THB": 40.971,
      "ZAR": 10.2562
    }
  },
  {
    "date": "2012-03-28",
    "base": "EUR",
    "rates": {
      "USD": 1.3337,
      "JPY": 110.74,
      "BGN": 1.9558,
      "CZK": 24.603,
      "DKK": 7.4361,
      "GBP": 0.839,
      "HUF": 292.66,
      "LTL": 3.4528,
      "LVL": 0.7005,
      "PLN": 4.1568,
      "RON": 4.3733,
      "SEK": 8.88,
      "CHF": 1.2063,
      "NOK": 7.611,
      "HRK": 7.506,
      "RUB": 38.9312,
      "TRY": 2.3763,
      "AUD": 1.2824,
      "BRL": 2.4262,
      "CAD": 1.3289,
      "CNY": 8.3967,
      "HKD": 10.3536,
      "IDR": 12232.74,
      "ILS": 4.962,
      "INR": 67.725,
      "KRW": 1514.05,
      "MXN": 16.9715,
      "MYR": 4.0834,
      "NZD": 1.6304,
      "PHP": 57.28,
      "SGD": 1.6761,
      "THB": 41.038,
      "ZAR": 10.203
    }
  },
  {
    "date": "2012-03-27",
    "base": "EUR",
    "rates": {
      "USD": 1.3333,
      "JPY": 110.57,
      "BGN": 1.9558,
      "CZK": 24.603,
      "DKK": 7.4357,
      "GBP": 0.8359,
      "HUF": 291.8,
      "LTL": 3.4528,
      "LVL": 0.6984,
      "PLN": 4.1367,
      "RON": 4.3725,
      "SEK": 8.8935,
      "CHF": 1.2056,
      "NOK": 7.571,
      "HRK": 7.5125,
      "RUB": 38.665,
      "TRY": 2.3809,
      "AUD": 1.2681,
      "BRL": 2.4271,
      "CAD": 1.3233,
      "CNY": 8.3974,
      "HKD": 10.3525,
      "IDR": 12208.57,
      "ILS": 4.9581,
      "INR": 67.698,
      "KRW": 1511.85,
      "MXN": 16.8782,
      "MYR": 4.0746,
      "NZD": 1.6203,
      "PHP": 57.26,
      "SGD": 1.6744,
      "THB": 40.946,
      "ZAR": 10.1035
    }
  },
  {
    "date": "2012-03-26",
    "base": "EUR",
    "rates": {
      "USD": 1.3276,
      "JPY": 109.82,
      "BGN": 1.9558,
      "CZK": 24.63,
      "DKK": 7.4356,
      "GBP": 0.8352,
      "HUF": 292.63,
      "LTL": 3.4528,
      "LVL": 0.6968,
      "PLN": 4.1376,
      "RON": 4.364,
      "SEK": 8.9277,
      "CHF": 1.2054,
      "NOK": 7.609,
      "HRK": 7.514,
      "RUB": 38.5,
      "TRY": 2.3767,
      "AUD": 1.2631,
      "BRL": 2.4021,
      "CAD": 1.3223,
      "CNY": 8.3699,
      "HKD": 10.3136,
      "IDR": 12184.35,
      "ILS": 4.949,
      "INR": 67.98,
      "KRW": 1513.68,
      "MXN": 16.8545,
      "MYR": 4.0817,
      "NZD": 1.6195,
      "PHP": 57.087,
      "SGD": 1.6734,
      "THB": 40.837,
      "ZAR": 10.1261
    }
  },
  {
    "date": "2012-03-23",
    "base": "EUR",
    "rates": {
      "USD": 1.3242,
      "JPY": 109.1,
      "BGN": 1.9558,
      "CZK": 24.725,
      "DKK": 7.4355,
      "GBP": 0.8363,
      "HUF": 294.48,
      "LTL": 3.4528,
      "LVL": 0.6969,
      "PLN": 4.1682,
      "RON": 4.3723,
      "SEK": 8.924,
      "CHF": 1.2054,
      "NOK": 7.638,
      "HRK": 7.5235,
      "RUB": 38.9144,
      "TRY": 2.3862,
      "AUD": 1.2745,
      "BRL": 2.4109,
      "CAD": 1.3263,
      "CNY": 8.345,
      "HKD": 10.2839,
      "IDR": 12127.58,
      "ILS": 4.9444,
      "INR": 67.898,
      "KRW": 1504.36,
      "MXN": 17.0186,
      "MYR": 4.0739,
      "NZD": 1.63,
      "PHP": 56.931,
      "SGD": 1.6748,
      "THB": 40.732,
      "ZAR": 10.2241
    }
  },
  {
    "date": "2012-03-22",
    "base": "EUR",
    "rates": {
      "USD": 1.3167,
      "JPY": 109.4,
      "BGN": 1.9558,
      "CZK": 24.736,
      "DKK": 7.4359,
      "GBP": 0.8333,
      "HUF": 293.5,
      "LTL": 3.4528,
      "LVL": 0.6968,
      "PLN": 4.1645,
      "RON": 4.373,
      "SEK": 8.9265,
      "CHF": 1.2055,
      "NOK": 7.624,
      "HRK": 7.5283,
      "RUB": 38.758,
      "TRY": 2.389,
      "AUD": 1.2696,
      "BRL": 2.4001,
      "CAD": 1.3151,
      "CNY": 8.3039,
      "HKD": 10.2252,
      "IDR": 12073.29,
      "ILS": 4.94,
      "INR": 67.448,
      "KRW": 1491.16,
      "MXN": 16.8642,
      "MYR": 4.0704,
      "NZD": 1.6294,
      "PHP": 56.74,
      "SGD": 1.668,
      "THB": 40.607,
      "ZAR": 10.166
    }
  },
  {
    "date": "2012-03-21",
    "base": "EUR",
    "rates": {
      "USD": 1.3225,
      "JPY": 111.11,
      "BGN": 1.9558,
      "CZK": 24.629,
      "DKK": 7.4354,
      "GBP": 0.83495,
      "HUF": 291.53,
      "LTL": 3.4528,
      "LVL": 0.6969,
      "PLN": 4.1525,
      "RON": 4.3755,
      "SEK": 8.9185,
      "CHF": 1.2058,
      "NOK": 7.6105,
      "HRK": 7.534,
      "RUB": 38.6748,
      "TRY": 2.3989,
      "AUD": 1.2644,
      "BRL": 2.4125,
      "CAD": 1.3093,
      "CNY": 8.3553,
      "HKD": 10.2689,
      "IDR": 12107.49,
      "ILS": 4.9469,
      "INR": 67.018,
      "KRW": 1493.87,
      "MXN": 16.7442,
      "MYR": 4.0692,
      "NZD": 1.6209,
      "PHP": 56.929,
      "SGD": 1.6708,
      "THB": 40.693,
      "ZAR": 10.1015
    }
  },
  {
    "date": "2012-03-20",
    "base": "EUR",
    "rates": {
      "USD": 1.3198,
      "JPY": 110.48,
      "BGN": 1.9558,
      "CZK": 24.464,
      "DKK": 7.4353,
      "GBP": 0.8322,
      "HUF": 289.38,
      "LTL": 3.4528,
      "LVL": 0.6966,
      "PLN": 4.127,
      "RON": 4.3788,
      "SEK": 8.912,
      "CHF": 1.2059,
      "NOK": 7.606,
      "HRK": 7.5335,
      "RUB": 38.6432,
      "TRY": 2.4,
      "AUD": 1.2586,
      "BRL": 2.4112,
      "CAD": 1.3098,
      "CNY": 8.3395,
      "HKD": 10.248,
      "IDR": 12083.74,
      "ILS": 4.9455,
      "INR": 66.594,
      "KRW": 1486.75,
      "MXN": 16.7681,
      "MYR": 4.0678,
      "NZD": 1.616,
      "PHP": 56.768,
      "SGD": 1.6672,
      "THB": 40.637,
      "ZAR": 10.0581
    }
  },
  {
    "date": "2012-03-19",
    "base": "EUR",
    "rates": {
      "USD": 1.315,
      "JPY": 109.73,
      "BGN": 1.9558,
      "CZK": 24.533,
      "DKK": 7.4356,
      "GBP": 0.82845,
      "HUF": 289.44,
      "LTL": 3.4528,
      "LVL": 0.6968,
      "PLN": 4.1255,
      "RON": 4.3788,
      "SEK": 8.877,
      "CHF": 1.2067,
      "NOK": 7.5505,
      "HRK": 7.5307,
      "RUB": 38.4562,
      "TRY": 2.3801,
      "AUD": 1.2452,
      "BRL": 2.3796,
      "CAD": 1.3037,
      "CNY": 8.3092,
      "HKD": 10.2086,
      "IDR": 11998.52,
      "ILS": 4.9481,
      "INR": 66.033,
      "KRW": 1476.89,
      "MXN": 16.6825,
      "MYR": 4.0147,
      "NZD": 1.5967,
      "PHP": 56.417,
      "SGD": 1.6549,
      "THB": 40.41,
      "ZAR": 9.9593
    }
  },
  {
    "date": "2012-03-16",
    "base": "EUR",
    "rates": {
      "USD": 1.3116,
      "JPY": 109.81,
      "BGN": 1.9558,
      "CZK": 24.511,
      "DKK": 7.4356,
      "GBP": 0.8295,
      "HUF": 290.64,
      "LTL": 3.4528,
      "LVL": 0.697,
      "PLN": 4.13,
      "RON": 4.3823,
      "SEK": 8.856,
      "CHF": 1.207,
      "NOK": 7.548,
      "HRK": 7.5368,
      "RUB": 38.479,
      "TRY": 2.3583,
      "AUD": 1.2401,
      "BRL": 2.3617,
      "CAD": 1.299,
      "CNY": 8.2926,
      "HKD": 10.1818,
      "IDR": 11997.04,
      "ILS": 4.93,
      "INR": 65.757,
      "KRW": 1475.65,
      "MXN": 16.57,
      "MYR": 4.0067,
      "NZD": 1.5942,
      "PHP": 56.387,
      "SGD": 1.6529,
      "THB": 40.332,
      "ZAR": 9.9661
    }
  },
  {
    "date": "2012-03-15",
    "base": "EUR",
    "rates": {
      "USD": 1.3057,
      "JPY": 108.82,
      "BGN": 1.9558,
      "CZK": 24.558,
      "DKK": 7.4348,
      "GBP": 0.83345,
      "HUF": 291.32,
      "LTL": 3.4528,
      "LVL": 0.6968,
      "PLN": 4.1393,
      "RON": 4.3792,
      "SEK": 8.916,
      "CHF": 1.2096,
      "NOK": 7.5665,
      "HRK": 7.5118,
      "RUB": 38.413,
      "TRY": 2.3555,
      "AUD": 1.2422,
      "BRL": 2.3468,
      "CAD": 1.296,
      "CNY": 8.2682,
      "HKD": 10.1354,
      "IDR": 11975.03,
      "ILS": 4.933,
      "INR": 65.775,
      "KRW": 1471.81,
      "MXN": 16.5456,
      "MYR": 3.9941,
      "NZD": 1.5988,
      "PHP": 56.154,
      "SGD": 1.6511,
      "THB": 40.176,
      "ZAR": 10.0038
    }
  },
  {
    "date": "2012-03-14",
    "base": "EUR",
    "rates": {
      "USD": 1.3062,
      "JPY": 109.16,
      "BGN": 1.9558,
      "CZK": 24.615,
      "DKK": 7.4349,
      "GBP": 0.8314,
      "HUF": 292.2,
      "LTL": 3.4528,
      "LVL": 0.6965,
      "PLN": 4.1545,
      "RON": 4.3655,
      "SEK": 8.883,
      "CHF": 1.211,
      "NOK": 7.547,
      "HRK": 7.5298,
      "RUB": 38.494,
      "TRY": 2.3459,
      "AUD": 1.2474,
      "BRL": 2.3614,
      "CAD": 1.2927,
      "CNY": 8.2719,
      "HKD": 10.139,
      "IDR": 11977.4,
      "ILS": 4.944,
      "INR": 65.343,
      "KRW": 1474.59,
      "MXN": 16.4549,
      "MYR": 3.9954,
      "NZD": 1.6082,
      "PHP": 56.025,
      "SGD": 1.6546,
      "THB": 40.205,
      "ZAR": 9.996
    }
  },
  {
    "date": "2012-03-13",
    "base": "EUR",
    "rates": {
      "USD": 1.3057,
      "JPY": 108.03,
      "BGN": 1.9558,
      "CZK": 24.585,
      "DKK": 7.4348,
      "GBP": 0.83575,
      "HUF": 294.37,
      "LTL": 3.4528,
      "LVL": 0.6966,
      "PLN": 4.1243,
      "RON": 4.3623,
      "SEK": 8.8889,
      "CHF": 1.206,
      "NOK": 7.4515,
      "HRK": 7.5365,
      "RUB": 38.7063,
      "TRY": 2.345,
      "AUD": 1.2444,
      "BRL": 2.3778,
      "CAD": 1.2953,
      "CNY": 8.2663,
      "HKD": 10.1342,
      "IDR": 11978.56,
      "ILS": 4.9373,
      "INR": 65.252,
      "KRW": 1469.15,
      "MXN": 16.5563,
      "MYR": 3.9641,
      "NZD": 1.5941,
      "PHP": 55.828,
      "SGD": 1.6482,
      "THB": 40.033,
      "ZAR": 9.892
    }
  },
  {
    "date": "2012-03-12",
    "base": "EUR",
    "rates": {
      "USD": 1.3119,
      "JPY": 107.79,
      "BGN": 1.9558,
      "CZK": 24.563,
      "DKK": 7.4348,
      "GBP": 0.8392,
      "HUF": 293.48,
      "LTL": 3.4528,
      "LVL": 0.6966,
      "PLN": 4.1095,
      "RON": 4.3553,
      "SEK": 8.9312,
      "CHF": 1.2056,
      "NOK": 7.4795,
      "HRK": 7.5475,
      "RUB": 38.845,
      "TRY": 2.3585,
      "AUD": 1.2498,
      "BRL": 2.3745,
      "CAD": 1.3026,
      "CNY": 8.3013,
      "HKD": 10.1784,
      "IDR": 12010.83,
      "ILS": 4.9627,
      "INR": 65.575,
      "KRW": 1474.62,
      "MXN": 16.648,
      "MYR": 3.9796,
      "NZD": 1.6092,
      "PHP": 55.911,
      "SGD": 1.6551,
      "THB": 40.21,
      "ZAR": 9.9555
    }
  },
  {
    "date": "2012-03-09",
    "base": "EUR",
    "rates": {
      "USD": 1.3191,
      "JPY": 107.93,
      "BGN": 1.9558,
      "CZK": 24.715,
      "DKK": 7.4352,
      "GBP": 0.83595,
      "HUF": 291.9,
      "LTL": 3.4528,
      "LVL": 0.6969,
      "PLN": 4.0992,
      "RON": 4.3555,
      "SEK": 8.9075,
      "CHF": 1.2053,
      "NOK": 7.46,
      "HRK": 7.549,
      "RUB": 38.729,
      "TRY": 2.3493,
      "AUD": 1.2415,
      "BRL": 2.3307,
      "CAD": 1.3091,
      "CNY": 8.3231,
      "HKD": 10.2331,
      "IDR": 12047.8,
      "ILS": 4.9851,
      "INR": 65.685,
      "KRW": 1475.32,
      "MXN": 16.746,
      "MYR": 3.9697,
      "NZD": 1.602,
      "PHP": 56.217,
      "SGD": 1.6519,
      "THB": 40.312,
      "ZAR": 9.918
    }
  },
  {
    "date": "2012-03-08",
    "base": "EUR",
    "rates": {
      "USD": 1.3242,
      "JPY": 108.18,
      "BGN": 1.9558,
      "CZK": 24.767,
      "DKK": 7.4344,
      "GBP": 0.83865,
      "HUF": 292.9,
      "LTL": 3.4528,
      "LVL": 0.6977,
      "PLN": 4.1135,
      "RON": 4.3558,
      "SEK": 8.8894,
      "CHF": 1.205,
      "NOK": 7.421,
      "HRK": 7.5575,
      "RUB": 39.3346,
      "TRY": 2.3514,
      "AUD": 1.2441,
      "BRL": 2.3298,
      "CAD": 1.3178,
      "CNY": 8.3664,
      "HKD": 10.272,
      "IDR": 12097.94,
      "ILS": 5.005,
      "INR": 66.7463,
      "KRW": 1477.43,
      "MXN": 16.9511,
      "MYR": 3.9772,
      "NZD": 1.6045,
      "PHP": 56.43,
      "SGD": 1.6593,
      "THB": 40.441,
      "ZAR": 9.9663
    }
  },
  {
    "date": "2012-03-07",
    "base": "EUR",
    "rates": {
      "USD": 1.312,
      "JPY": 105.95,
      "BGN": 1.9558,
      "CZK": 24.871,
      "DKK": 7.4345,
      "GBP": 0.8349,
      "HUF": 296.28,
      "LTL": 3.4528,
      "LVL": 0.6978,
      "PLN": 4.1644,
      "RON": 4.358,
      "SEK": 8.924,
      "CHF": 1.2052,
      "NOK": 7.448,
      "HRK": 7.5588,
      "RUB": 39.0299,
      "TRY": 2.3459,
      "AUD": 1.2423,
      "BRL": 2.3209,
      "CAD": 1.314,
      "CNY": 8.2855,
      "HKD": 10.1858,
      "IDR": 12037.6,
      "ILS": 5.0022,
      "INR": 66.131,
      "KRW": 1476.91,
      "MXN": 17.0308,
      "MYR": 3.9714,
      "NZD": 1.6043,
      "PHP": 56.37,
      "SGD": 1.6554,
      "THB": 40.37,
      "ZAR": 10.0432
    }
  },
  {
    "date": "2012-03-06",
    "base": "EUR",
    "rates": {
      "USD": 1.3153,
      "JPY": 106.66,
      "BGN": 1.9558,
      "CZK": 24.866,
      "DKK": 7.4344,
      "GBP": 0.83255,
      "HUF": 293.43,
      "LTL": 3.4528,
      "LVL": 0.6981,
      "PLN": 4.1495,
      "RON": 4.3538,
      "SEK": 8.8906,
      "CHF": 1.2055,
      "NOK": 7.452,
      "HRK": 7.5548,
      "RUB": 38.8666,
      "TRY": 2.3485,
      "AUD": 1.2418,
      "BRL": 2.3007,
      "CAD": 1.3137,
      "CNY": 8.3024,
      "HKD": 10.2103,
      "IDR": 12080.27,
      "ILS": 5.0127,
      "INR": 66.271,
      "KRW": 1479.71,
      "MXN": 16.9779,
      "MYR": 3.9854,
      "NZD": 1.615,
      "PHP": 56.624,
      "SGD": 1.6604,
      "THB": 40.485,
      "ZAR": 10.0079
    }
  },
  {
    "date": "2012-03-05",
    "base": "EUR",
    "rates": {
      "USD": 1.322,
      "JPY": 107.54,
      "BGN": 1.9558,
      "CZK": 24.78,
      "DKK": 7.4341,
      "GBP": 0.83465,
      "HUF": 291.26,
      "LTL": 3.4528,
      "LVL": 0.698,
      "PLN": 4.126,
      "RON": 4.3503,
      "SEK": 8.8382,
      "CHF": 1.2061,
      "NOK": 7.42,
      "HRK": 7.5645,
      "RUB": 38.712,
      "TRY": 2.3355,
      "AUD": 1.2354,
      "BRL": 2.2844,
      "CAD": 1.3129,
      "CNY": 8.3392,
      "HKD": 10.2628,
      "IDR": 12069.54,
      "ILS": 5.0192,
      "INR": 65.829,
      "KRW": 1478.08,
      "MXN": 16.9126,
      "MYR": 3.9905,
      "NZD": 1.604,
      "PHP": 56.659,
      "SGD": 1.6608,
      "THB": 40.506,
      "ZAR": 9.9892
    }
  },
  {
    "date": "2012-03-02",
    "base": "EUR",
    "rates": {
      "USD": 1.3217,
      "JPY": 107.74,
      "BGN": 1.9558,
      "CZK": 24.715,
      "DKK": 7.4346,
      "GBP": 0.8327,
      "HUF": 289.3,
      "LTL": 3.4528,
      "LVL": 0.6983,
      "PLN": 4.1074,
      "RON": 4.3508,
      "SEK": 8.8316,
      "CHF": 1.2062,
      "NOK": 7.4205,
      "HRK": 7.5673,
      "RUB": 38.7275,
      "TRY": 2.3277,
      "AUD": 1.2264,
      "BRL": 2.2712,
      "CAD": 1.3044,
      "CNY": 8.3237,
      "HKD": 10.2548,
      "IDR": 12020,
      "ILS": 5.0187,
      "INR": 65.371,
      "KRW": 1474.72,
      "MXN": 16.8678,
      "MYR": 3.9701,
      "NZD": 1.5851,
      "PHP": 56.482,
      "SGD": 1.6527,
      "THB": 40.404,
      "ZAR": 9.9265
    }
  },
  {
    "date": "2012-03-01",
    "base": "EUR",
    "rates": {
      "USD": 1.3312,
      "JPY": 107.95,
      "BGN": 1.9558,
      "CZK": 24.89,
      "DKK": 7.4346,
      "GBP": 0.8349,
      "HUF": 287.86,
      "LTL": 3.4528,
      "LVL": 0.6986,
      "PLN": 4.1152,
      "RON": 4.3505,
      "SEK": 8.8135,
      "CHF": 1.2052,
      "NOK": 7.4225,
      "HRK": 7.567,
      "RUB": 39.033,
      "TRY": 2.3343,
      "AUD": 1.2353,
      "BRL": 2.2886,
      "CAD": 1.312,
      "CNY": 8.3859,
      "HKD": 10.3245,
      "IDR": 12097.04,
      "ILS": 5.0349,
      "INR": 65.595,
      "KRW": 1488.9,
      "MXN": 17.0633,
      "MYR": 3.9989,
      "NZD": 1.5909,
      "PHP": 57.026,
      "SGD": 1.6635,
      "THB": 40.735,
      "ZAR": 9.9496
    }
  }
]